Workbook
Name Flow0.: 'Planning Model'!#REF!
Name Flow0._1: 'Planning Model'!$B$12:$V$20
Name Flow0._2: 'Planning Model'!$AB$12:$AX$20
Name Flow0._3: 'Planning Model'!$AC$82:$AX$90
Name Flow1._1: 'Planning Model'!$B$25:$V$75
Name Flow2._1: 'Planning Model'!$A$135:$V$189

Sheet Planning Model
A1: Revenue | E1: =SUMPRODUCT(E317:V344,E255:V282) -> 35125544 | H1: Yellow Cells | J1: model inputs
A2: Production cost | E2: =SUMPRODUCT(E230:V237,E241:V248) -> 20064800 | H2: Green Cells | J2: model decisions variables
A3: Inventory Holding Cost at sources | E3: =SUM(AY13:AY20) -> 8903.3991 | H3: Tan Cells | J3: model intermediate variables,as determined by the decision variabiles and the inputs
A4: Inventory Holding costs at regions | E4: =SUM(AY58:AY71) -> 104706.81
A5: Transportation Cost: Source to Storage | E5: =SUM(W26:W75) -> 8610594.3
A6: Transportation Cost: Buffer to Storage | E6: =SUM(W81:W130) -> 700050.17
A7: Transshipment Cost: Storage to Region | E7: =SUM(W136:W189) -> 1032887.6
A9: Net profit | E9: =E1-SUM(E2:E7) -> 4603601
A11: Flow from source to buffer location | AB11: Inventory at Buffer locations;
A12: Product | B12: SourceID | E12: Mar 21 | F12: Apr 21 | G12: May 21 | H12: Jun 21 | I12: Jul 21 | J12: Aug 21 | K12: Sep 21 | L12: Oct 21 | M12: Nov 21 | N12: Dec 21 | O12: Jan 22 | P12: Feb 22 | Q12: Mar 22 | R12: Apr 22 | S12: May 22 | T12: Jun 22 | U12: Jul 22 | V12: Aug 22 | AB12: Product | AC12: SourceID | AD12: Capacity (tons) | AE12: Monthly Cost/Ton | AF12: 44236 | AG12: Mar 21 | AH12: Apr 21 | AI12: May 21 | AJ12: Jun 21 | AK12: Jul 21 | AL12: Aug 21 | AM12: Sep 21 | AN12: Oct 21 | AO12: Nov 21 | AP12: Dec 21 | AQ12: Jan 22 | AR12: Feb 22 | AS12: Mar 22 | AT12: Apr 22 | AU12: May 22 | AV12: Jun 22 | AW12: Jul 22 | AX12: Aug 22 | AY12: total cost
A13: SW | B13: ARGT | E13: 100 | F13: 0 | G13: 0 | H13: 0 | I13: 0 | J13: 0 | K13: 0 | L13: 0 | M13: 100 | N13: 0 | O13: 0 | P13: 0 | Q13: 0 | R13: 0 | S13: 0 | T13: 0 | U13: 0 | V13: 0 | AB13: SW | AC13: ARGT | AD13: 100 | AE13: 0.33333333 | AF13: 0 | AG13: =AF13+E13-SUM('Planning Model'!E81:E84) -> 100 | AH13: =AG13+F13-SUM('Planning Model'!F81:F84) -> 100 | AI13: =AH13+G13-SUM('Planning Model'!G81:G84) -> 100 | AJ13: =AI13+H13-SUM('Planning Model'!H81:H84) -> 100 | AK13: =AJ13+I13-SUM('Planning Model'!I81:I84) -> 100 | AL13: =AK13+J13-SUM('Planning Model'!J81:J84) -> 100 | AM13: =AL13+K13-SUM('Planning Model'!K81:K84) -> 0 | AN13: =AM13+L13-SUM('Planning Model'!L81:L84) -> 0 | ... AX13: =AW13+V13-SUM('Planning Model'!V81:V84) -> 0 | AY13: =AE13*SUM(AG13:AX13) -> 500
A14: SW | B14: CRTH | E14: 200 | F14: 0 | G14: 0 | H14: 0 | I14: 0 | J14: 0 | K14: 0 | L14: 0 | M14: 0 | N14: 56.17584 | O14: 56.17584 | P14: 87.64832 | Q14: 0 | R14: 0 | S14: 0 | T14: 0 | U14: 0 | V14: 0 | AB14: SW | AC14: CRTH | AD14: 200 | AE14: 0.16666667 | AF14: 0 | AG14: =AF14+'Planning Model'!E14-SUM('Planning Model'!E85:E89) -> 200 | AH14: =AG14+'Planning Model'!F14-SUM('Planning Model'!F85:F89) -> 200 | AI14: =AH14+'Planning Model'!G14-SUM('Planning Model'!G85:G89) -> 200 | AJ14: =AI14+'Planning Model'!H14-SUM('Planning Model'!H85:H89) -> 200 | AK14: =AJ14+'Planning Model'!I14-SUM('Planning Model'!I85:I89) -> 200 | AL14: =AK14+'Planning Model'!J14-SUM('Planning Model'!J85:J89) -> 200 | AM14: =AL14+'Planning Model'!K14-SUM('Planning Model'!K85:K89) -> 200 | AN14: =AM14+'Planning Model'!L14-SUM('Planning Model'!L85:L89) -> 0 | ... AX14: =AW14+'Planning Model'!V14-SUM('Planning Model'!V85:V89) -> 0 | AY14: =AE14*SUM(AG14:AX14) -> 461.42125
A15: HW | B15: HASS | E15: 99.126 | F15: 184.34752 | G15: 162.66685 | H15: 53.859628 | I15: 0 | J15: 0 | K15: 0 | L15: 0 | M15: 82.005766 | N15: 0 | O15: 0 | P15: 0 | Q15: 0 | R15: 0 | S15: 0 | T15: 0 | U15: 0 | V15: 0 | AB15: HW | AC15: HASS | AD15: 500 | AE15: 0.16666667 | AF15: 0 | AG15: =AF15+'Planning Model'!E15-SUM('Planning Model'!E90:E97) -> 99.126 | AH15: =AG15+'Planning Model'!F15-SUM('Planning Model'!F90:F97) -> 283.47352 | AI15: =AH15+'Planning Model'!G15-SUM('Planning Model'!G90:G97) -> 446.14037 | AJ15: =AI15+'Planning Model'!H15-SUM('Planning Model'!H90:H97) -> 500 | AK15: =AJ15+'Planning Model'!I15-SUM('Planning Model'!I90:I97) -> 500 | AL15: =AK15+'Planning Model'!J15-SUM('Planning Model'!J90:J97) -> 500 | AM15: =AL15+'Planning Model'!K15-SUM('Planning Model'!K90:K97) -> 500 | AN15: =AM15+'Planning Model'!L15-SUM('Planning Model'!L90:L97) -> 417.99423 | ... AX15: =AW15+'Planning Model'!V15-SUM('Planning Model'!V90:V97) -> -1.9999999e-06 | AY15: =AE15*SUM(AG15:AX15) -> 1269.3903
A16: HW | B16: JAFF | E16: 100 | F16: 0 | G16: 0 | H16: 0 | I16: 0 | J16: 0 | K16: 0 | L16: 0 | M16: 0 | N16: 0 | O16: 0 | P16: 0 | Q16: 100 | R16: 0 | S16: 0 | T16: 0 | U16: 0 | V16: 0 | AB16: HW | AC16: JAFF | AD16: 100 | AE16: 0.33333333 | AF16: 0 | AG16: =AF16+'Planning Model'!E16-SUM('Planning Model'!E98:E101) -> 100 | AH16: =AG16+'Planning Model'!F16-SUM('Planning Model'!F98:F101) -> 100 | AI16: =AH16+'Planning Model'!G16-SUM('Planning Model'!G98:G101) -> 100 | AJ16: =AI16+'Planning Model'!H16-SUM('Planning Model'!H98:H101) -> 100 | AK16: =AJ16+'Planning Model'!I16-SUM('Planning Model'!I98:I101) -> 100 | AL16: =AK16+'Planning Model'!J16-SUM('Planning Model'!J98:J101) -> 100 | AM16: =AL16+'Planning Model'!K16-SUM('Planning Model'!K98:K101) -> 100 | AN16: =AM16+'Planning Model'!L16-SUM('Planning Model'!L98:L101) -> 100 | ... AX16: =AW16+'Planning Model'!V16-SUM('Planning Model'!V98:V101) -> 0 | AY16: =AE16*SUM(AG16:AX16) -> 482.38337
A17: HW | B17: MICH | E17: 90 | F17: 10 | G17: 0 | H17: 0 | I17: 0 | J17: 0 | K17: 0 | L17: 0 | M17: 0 | N17: 0 | O17: 0 | P17: 100 | Q17: 0 | R17: 0 | S17: 0 | T17: 0 | U17: 0 | V17: 0 | AB17: HW | AC17: MICH | AD17: 100 | AE17: 0.25 | AF17: 0 | AG17: =AF17+'Planning Model'!E17-SUM('Planning Model'!E102:E103) -> 90 | AH17: =AG17+'Planning Model'!F17-SUM('Planning Model'!F102:F103) -> 100 | AI17: =AH17+'Planning Model'!G17-SUM('Planning Model'!G102:G103) -> 100 | AJ17: =AI17+'Planning Model'!H17-SUM('Planning Model'!H102:H103) -> 100 | AK17: =AJ17+'Planning Model'!I17-SUM('Planning Model'!I102:I103) -> 100 | AL17: =AK17+'Planning Model'!J17-SUM('Planning Model'!J102:J103) -> 100 | AM17: =AL17+'Planning Model'!K17-SUM('Planning Model'!K102:K103) -> 100 | AN17: =AM17+'Planning Model'!L17-SUM('Planning Model'!L102:L103) -> 100 | ... AX17: =AW17+'Planning Model'!V17-SUM('Planning Model'!V102:V103) -> 0 | AY17: =AE17*SUM(AG17:AX17) -> 347.5
A18: SW | B18: PRIN | E18: 450 | F18: 450 | G18: 100 | H18: 0 | I18: 0 | J18: 0 | K18: 0 | L18: 0 | M18: 0 | N18: 0 | O18: 0 | P18: 0 | Q18: 0 | R18: 588.41401 | S18: 411.58599 | T18: 0 | U18: 0 | V18: 0 | AB18: SW | AC18: PRIN | AD18: 1000 | AE18: 0.25 | AF18: 0 | AG18: =AF18+E18-SUM('Planning Model'!E104:E114) -> 450 | AH18: =AG18+F18-SUM('Planning Model'!F104:F114) -> 900 | AI18: =AH18+G18-SUM('Planning Model'!G104:G114) -> 1000 | AJ18: =AI18+H18-SUM('Planning Model'!H104:H114) -> 1000 | AK18: =AJ18+I18-SUM('Planning Model'!I104:I114) -> 1000 | AL18: =AK18+J18-SUM('Planning Model'!J104:J114) -> 1000 | AM18: =AL18+K18-SUM('Planning Model'!K104:K114) -> 663.00035 | AN18: =AM18+L18-SUM('Planning Model'!L104:L114) -> 345.15619 | ... AX18: =AW18+V18-SUM('Planning Model'!V104:V114) -> 2e-06 | AY18: =AE18*SUM(AG18:AX18) -> 2543.9391
A19: HW | B19: SCHY | E19: 100 | F19: 0 | G19: 0 | H19: 0 | I19: 0 | J19: 0 | K19: 0 | L19: 0 | M19: 100 | N19: 0 | O19: 0 | P19: 0 | Q19: 0 | R19: 100 | S19: 0 | T19: 0 | U19: 0 | V19: 0 | AB19: HW | AC19: SCHY | AD19: 100 | AE19: 0.16666667 | AF19: 0 | AG19: =AF19+E19-SUM('Planning Model'!E115:E121) -> 100 | AH19: =AG19+F19-SUM('Planning Model'!F115:F121) -> 100 | AI19: =AH19+G19-SUM('Planning Model'!G115:G121) -> 100 | AJ19: =AI19+H19-SUM('Planning Model'!H115:H121) -> 100 | AK19: =AJ19+I19-SUM('Planning Model'!I115:I121) -> 100 | AL19: =AK19+J19-SUM('Planning Model'!J115:J121) -> 100 | AM19: =AL19+K19-SUM('Planning Model'!K115:K121) -> 100 | AN19: =AM19+L19-SUM('Planning Model'!L115:L121) -> 0 | ... AX19: =AW19+V19-SUM('Planning Model'!V115:V121) -> 0 | AY19: =AE19*SUM(AG19:AX19) -> 250
A20: SW | B20: STFC | E20: 1000 | F20: 0 | G20: 0 | H20: 0 | I20: 0 | J20: 0 | K20: 0 | L20: 0 | M20: 0 | N20: 22.199177 | O20: 287.09685 | P20: 408.34185 | Q20: 282.36212 | R20: 0 | S20: 0 | T20: 0 | U20: 0 | V20: 0 | AB20: SW | AC20: STFC | AD20: 1000 | AE20: 0.25 | AF20: 0 | AG20: =AF20+E20-SUM('Planning Model'!E122:E130) -> 1000 | AH20: =AG20+F20-SUM('Planning Model'!F122:F130) -> 1000 | AI20: =AH20+G20-SUM('Planning Model'!G122:G130) -> 1000 | AJ20: =AI20+H20-SUM('Planning Model'!H122:H130) -> 1000 | AK20: =AJ20+I20-SUM('Planning Model'!I122:I130) -> 1000 | AL20: =AK20+J20-SUM('Planning Model'!J122:J130) -> 1000 | AM20: =AL20+K20-SUM('Planning Model'!K122:K130) -> 145.92717 | AN20: =AM20+L20-SUM('Planning Model'!L122:L130) -> 0 | ... AX20: =AW20+V20-SUM('Planning Model'!V122:V130) -> -2.9999999e-06 | AY20: =AE20*SUM(AG20:AX20) -> 3048.7651
A24: Flow from source to depot storage points | AB24: Inventory at depot storage points
B25: SourceID | C25: StorID | D25: Cost/ton | E25: Mar 21 | F25: Apr 21 | G25: May 21 | H25: Jun 21 | I25: Jul 21 | J25: Aug 21 | K25: Sep 21 | L25: Oct 21 | M25: Nov 21 | N25: Dec 21 | O25: Jan 22 | P25: Feb 22 | Q25: Mar 22 | R25: Apr 22 | S25: May 22 | T25: Jun 22 | U25: Jul 22 | V25: Aug 22 | W25: Total Cost | AB25: Product | AC25: regionID | AF25: 44236 | AG25: Mar 21 | AH25: Apr 21 | AI25: May 21 | AJ25: Jun 21 | AK25: Jul 21 | AL25: Aug 21 | AM25: Sep 21 | AN25: Oct 21 | AO25: Nov 21 | AP25: Dec 21 | AQ25: Jan 22 | AR25: Feb 22 | AS25: Mar 22 | AT25: Apr 22 | AU25: May 22 | AV25: Jun 22 | AW25: Jul 22 | AX25: Aug 22
A26: SW | B26: ARGT | C26: CJER | D26: 58.333333 | E26: 850.5 | F26: 0 | G26: 0 | H26: 0 | I26: 0 | J26: 0 | K26: 0 | L26: 0 | M26: 0 | N26: 0 | O26: 0 | P26: 0 | Q26: 0 | R26: 0 | S26: 0 | T26: 0 | U26: 0 | V26: 0 | W26: =D26*SUM(E26:V26) -> 49612.5 | AB26: HW | AC26: BERK | AF26: 300 | AG26: =AF26+'Planning Model'!E43+'Planning Model'!E98+'Planning Model'!E60+'Planning Model'!E115-'Planning Model'!E137 -> 284.17531 | AH26: =AG26+'Planning Model'!F43+'Planning Model'!F98+'Planning Model'!F60+'Planning Model'!F115-'Planning Model'!F137 -> 814.93398 | AI26: =AH26+'Planning Model'!G43+'Planning Model'!G98+'Planning Model'!G60+'Planning Model'!G115-'Planning Model'!G137 -> 949.99999 | AJ26: =AI26+'Planning Model'!H43+'Planning Model'!H98+'Planning Model'!H60+'Planning Model'!H115-'Planning Model'!H137 -> 788.23489 | AK26: =AJ26+'Planning Model'!I43+'Planning Model'!I98+'Planning Model'!I60+'Planning Model'!I115-'Planning Model'!I137 -> 647.26452 | AL26: =AK26+'Planning Model'!J43+'Planning Model'!J98+'Planning Model'!J60+'Planning Model'!J115-'Planning Model'!J137 -> 509.83435 | AM26: =AL26+'Planning Model'!K43+'Planning Model'!K98+'Planning Model'!K60+'Planning Model'!K115-'Planning Model'!K137 -> 296.97546 | AN26: =AM26+'Planning Model'!L43+'Planning Model'!L98+'Planning Model'!L60+'Planning Model'!L115-'Planning Model'!L137 -> 83.733852 | ... AX26: =AW26+'Planning Model'!V43+'Planning Model'!V98+'Planning Model'!V60+'Planning Model'!V115-'Planning Model'!V137 -> -1.6999999e-06
A27: SW | B27: ARGT | C27: HUDV | D27: 41.666667 | E27: 49.5 | F27: 1000 | G27: 635.85506 | H27: 985.7295 | I27: 798.51655 | J27: 292.46568 | K27: 788.05632 | L27: 842.84018 | M27: 878.19557 | N27: 162.18707 | O27: 162.18707 | P27: 371.08529 | Q27: 455.34875 | R27: 1390.5406 | S27: 1255.5663 | T27: 1256.8051 | U27: 883.59365 | V27: 682.81785 | W27: =D27*SUM(E27:V27) -> 537137.11 | AB27: HW | AC27: CJER | AF27: 0 | AG27: =AF27+'Planning Model'!E35+'Planning Model'!E61+'Planning Model'!E90+'Planning Model'!E116-'Planning Model'!E138 -> 109.62 | AH27: =AG27+'Planning Model'!F35+'Planning Model'!F61+'Planning Model'!F90+'Planning Model'!F116-'Planning Model'!F138 -> 105.84 | AI27: =AH27+'Planning Model'!G35+'Planning Model'!G61+'Planning Model'!G90+'Planning Model'!G116-'Planning Model'!G138 -> 100.17 | AJ27: =AI27+'Planning Model'!H35+'Planning Model'!H61+'Planning Model'!H90+'Planning Model'!H116-'Planning Model'!H138 -> 97.335 | AK27: =AJ27+'Planning Model'!I35+'Planning Model'!I61+'Planning Model'!I90+'Planning Model'!I116-'Planning Model'!I138 -> 92.61 | AL27: =AK27+'Planning Model'!J35+'Planning Model'!J61+'Planning Model'!J90+'Planning Model'!J116-'Planning Model'!J138 -> 86.94 | AM27: =AL27+'Planning Model'!K35+'Planning Model'!K61+'Planning Model'!K90+'Planning Model'!K116-'Planning Model'!K138 -> 77.49 | AN27: =AM27+'Planning Model'!L35+'Planning Model'!L61+'Planning Model'!L90+'Planning Model'!L116-'Planning Model'!L138 -> 63.315 | ... AX27: =AW27+'Planning Model'!V35+'Planning Model'!V61+'Planning Model'!V90+'Planning Model'!V116-'Planning Model'!V138 -> 1.2878587e-14
A28: SW | B28: ARGT | C28: NJER | D28: 41.666667 | E28: 0 | F28: 0 | G28: 227.37625 | H28: 0 | I28: 201.48345 | J28: 241.542 | K28: 285.00255 | L28: 371.58345 | M28: 160.14915 | N28: 107.24805 | O28: 107.24805 | P28: 85.79844 | Q28: 44.65125 | R28: 109.45935 | S28: 244.4337 | T28: 243.19489 | U28: 301.55036 | V28: 362.313 | W28: =D28*SUM(E28:V28) -> 128876.41 | AB28: HW | AC28: CTRI | AF28: 0 | AG28: =AF28-'Planning Model'!E139-'Planning Model'!E143-'Planning Model'!E152-'Planning Model'!E159 -> 0 | AH28: =AG28-'Planning Model'!F139-'Planning Model'!F143-'Planning Model'!F152-'Planning Model'!F159 -> 0 | AI28: =AH28-'Planning Model'!G139-'Planning Model'!G143-'Planning Model'!G152-'Planning Model'!G159 -> 0 | AJ28: =AI28-'Planning Model'!H139-'Planning Model'!H143-'Planning Model'!H152-'Planning Model'!H159 -> 0 | AK28: =AJ28-'Planning Model'!I139-'Planning Model'!I143-'Planning Model'!I152-'Planning Model'!I159 -> 0 | AL28: =AK28-'Planning Model'!J139-'Planning Model'!J143-'Planning Model'!J152-'Planning Model'!J159 -> 0 | AM28: =AL28-'Planning Model'!K139-'Planning Model'!K143-'Planning Model'!K152-'Planning Model'!K159 -> 0 | AN28: =AM28-'Planning Model'!L139-'Planning Model'!L143-'Planning Model'!L152-'Planning Model'!L159 -> 0 | ... AX28: =AW28-'Planning Model'!V139-'Planning Model'!V143-'Planning Model'!V152-'Planning Model'!V159 -> 0
A29: SW | B29: ARGT | C29: WTCT | D29: 50 | E29: 0 | F29: 0 | G29: 136.76869 | H29: 14.2705 | I29: 0 | J29: 965.99232 | K29: 426.94113 | L29: 285.57637 | M29: 361.65528 | N29: 230.56488 | O29: 230.56488 | P29: 43.116272 | Q29: 0 | R29: 0 | S29: 0 | T29: 0 | U29: 314.85599 | V29: 954.86915 | W29: =D29*SUM(E29:V29) -> 198258.77 | AB29: HW | AC29: DEME | AF29: 0 | AG29: =AF29-'Planning Model'!E140 -> 0 | AH29: =AG29-'Planning Model'!F140 -> 0 | AI29: =AH29-'Planning Model'!G140 -> 0 | AJ29: =AI29-'Planning Model'!H140 -> 0 | AK29: =AJ29-'Planning Model'!I140 -> 0 | AL29: =AK29-'Planning Model'!J140 -> 0 | AM29: =AL29-'Planning Model'!K140 -> 0 | AN29: =AM29-'Planning Model'!L140 -> 0 | ... AX29: =AW29-'Planning Model'!V140 -> 0
A30: SW | B30: CRTH | C30: DEME | D30: 41.666667 | E30: 0 | F30: 0 | G30: 0 | H30: 0 | I30: 0 | J30: 0 | K30: 0 | L30: 0 | M30: 0 | N30: 0 | O30: 0 | P30: 0 | Q30: 0 | R30: 0 | S30: 0 | T30: 0 | U30: 0 | V30: 0 | W30: =D30*SUM(E30:V30) -> 0 | AB30: HW | AC30: HUDV | AF30: 300 | AG30: =AF30+'Planning Model'!E36+'Planning Model'!E62+'Planning Model'!E91+'Planning Model'!E117-'Planning Model'!E142 -> 723.68719 | AH30: =AG30+'Planning Model'!F36+'Planning Model'!F62+'Planning Model'!F91+'Planning Model'!F117-'Planning Model'!F142 -> 646.26511 | AI30: =AH30+'Planning Model'!G36+'Planning Model'!G62+'Planning Model'!G91+'Planning Model'!G117-'Planning Model'!G142 -> 550.88685 | AJ30: =AI30+'Planning Model'!H36+'Planning Model'!H62+'Planning Model'!H91+'Planning Model'!H117-'Planning Model'!H142 -> 403.02743 | AK30: =AJ30+'Planning Model'!I36+'Planning Model'!I62+'Planning Model'!I91+'Planning Model'!I117-'Planning Model'!I142 -> 308.57941 | AL30: =AK30+'Planning Model'!J36+'Planning Model'!J62+'Planning Model'!J91+'Planning Model'!J117-'Planning Model'!J142 -> 121.88934 | AM30: =AL30+'Planning Model'!K36+'Planning Model'!K62+'Planning Model'!K91+'Planning Model'!K117-'Planning Model'!K142 -> 1.2e-05 | AN30: =AM30+'Planning Model'!L36+'Planning Model'!L62+'Planning Model'!L91+'Planning Model'!L117-'Planning Model'!L142 -> 1.5e-05 | ... AX30: =AW30+'Planning Model'!V36+'Planning Model'!V62+'Planning Model'!V91+'Planning Model'!V117-'Planning Model'!V142 -> 1.9e-05
A31: SW | B31: CRTH | C31: NCMA | D31: 58.333333 | E31: 0 | F31: 0 | G31: 0 | H31: 0 | I31: 0 | J31: 0 | K31: 0 | L31: 0 | M31: 0 | N31: 0 | O31: 0 | P31: 0 | Q31: 0 | R31: 0 | S31: 0 | T31: 0 | U31: 0 | V31: 0 | W31: =D31*SUM(E31:V31) -> 0 | AB31: HW | AC31: NCMA | AF31: 250 | AG31: =AF31+'Planning Model'!E37+'Planning Model'!E63+'Planning Model'!E92+'Planning Model'!E118-'Planning Model'!E146 -> 199.4425 | AH31: =AG31+'Planning Model'!F37+'Planning Model'!F63+'Planning Model'!F92+'Planning Model'!F118-'Planning Model'!F146 -> 70.9603 | AI31: =AH31+'Planning Model'!G37+'Planning Model'!G63+'Planning Model'!G92+'Planning Model'!G118-'Planning Model'!G146 -> 8.05011 | AJ31: =AI31+'Planning Model'!H37+'Planning Model'!H63+'Planning Model'!H92+'Planning Model'!H118-'Planning Model'!H146 -> 104.16641 | AK31: =AJ31+'Planning Model'!I37+'Planning Model'!I63+'Planning Model'!I92+'Planning Model'!I118-'Planning Model'!I146 -> 0 | AL31: =AK31+'Planning Model'!J37+'Planning Model'!J63+'Planning Model'!J92+'Planning Model'!J118-'Planning Model'!J146 -> 0 | AM31: =AL31+'Planning Model'!K37+'Planning Model'!K63+'Planning Model'!K92+'Planning Model'!K118-'Planning Model'!K146 -> 0 | AN31: =AM31+'Planning Model'!L37+'Planning Model'!L63+'Planning Model'!L92+'Planning Model'!L118-'Planning Model'!L146 -> 3e-06 | ... AX31: =AW31+'Planning Model'!V37+'Planning Model'!V63+'Planning Model'!V92+'Planning Model'!V118-'Planning Model'!V146 -> 9.9999997e-06
A32: SW | B32: CRTH | C32: SCST | D32: 50 | E32: 0 | F32: 315 | G32: 315 | H32: 315 | I32: 315 | J32: 315 | K32: 315 | L32: 315 | M32: 315 | N32: 258.82416 | O32: 258.82416 | P32: 207.05933 | Q32: 99.792 | R32: 654.2046 | S32: 1050 | T32: 1050 | U32: 1050 | V32: 1050 | W32: =D32*SUM(E32:V32) -> 409935.21 | AB32: HW | AC32: NJER | AF32: 50 | AG32: =AF32+'Planning Model'!E38+'Planning Model'!E64+'Planning Model'!E93+'Planning Model'!E119-'Planning Model'!E147 -> 46.6925 | AH32: =AG32+'Planning Model'!F38+'Planning Model'!F64+'Planning Model'!F93+'Planning Model'!F119-'Planning Model'!F147 -> 38.5844 | AI32: =AH32+'Planning Model'!G38+'Planning Model'!G64+'Planning Model'!G93+'Planning Model'!G119-'Planning Model'!G147 -> 20.4782 | AJ32: =AI32+'Planning Model'!H38+'Planning Model'!H64+'Planning Model'!H93+'Planning Model'!H119-'Planning Model'!H147 -> 2.51375 | AK32: =AJ32+'Planning Model'!I38+'Planning Model'!I64+'Planning Model'!I93+'Planning Model'!I119-'Planning Model'!I147 -> 0 | AL32: =AK32+'Planning Model'!J38+'Planning Model'!J64+'Planning Model'!J93+'Planning Model'!J119-'Planning Model'!J147 -> 0 | AM32: =AL32+'Planning Model'!K38+'Planning Model'!K64+'Planning Model'!K93+'Planning Model'!K119-'Planning Model'!K147 -> 0 | AN32: =AM32+'Planning Model'!L38+'Planning Model'!L64+'Planning Model'!L93+'Planning Model'!L119-'Planning Model'!L147 -> 0 | ... AX32: =AW32+'Planning Model'!V38+'Planning Model'!V64+'Planning Model'!V93+'Planning Model'!V119-'Planning Model'!V147 -> 0
A33: SW | B33: CRTH | C33: SEMA | D33: 66.666667 | E33: 0 | F33: 0 | G33: 0 | H33: 0 | I33: 0 | J33: 0 | K33: 0 | L33: 0 | M33: 0 | N33: 0 | O33: 0 | P33: 0 | Q33: 0 | R33: 0 | S33: 0 | T33: 0 | U33: 0 | V33: 0 | W33: =D33*SUM(E33:V33) -> 0 | AB33: HW | AC33: OHIO | AF33: 200 | AG33: =AF33+'Planning Model'!E39+'Planning Model'!E47+'Planning Model'!E94+'Planning Model'!E102-'Planning Model'!E148 -> 195.1805 | AH33: =AG33+'Planning Model'!F39+'Planning Model'!F47+'Planning Model'!F94+'Planning Model'!F102-'Planning Model'!F148 -> 189.80534 | AI33: =AH33+'Planning Model'!G39+'Planning Model'!G47+'Planning Model'!G94+'Planning Model'!G102-'Planning Model'!G148 -> 185.56985 | AJ33: =AI33+'Planning Model'!H39+'Planning Model'!H47+'Planning Model'!H94+'Planning Model'!H102-'Planning Model'!H148 -> 180.10113 | AK33: =AJ33+'Planning Model'!I39+'Planning Model'!I47+'Planning Model'!I94+'Planning Model'!I102-'Planning Model'!I148 -> 172.33607 | AL33: =AK33+'Planning Model'!J39+'Planning Model'!J47+'Planning Model'!J94+'Planning Model'!J102-'Planning Model'!J148 -> 162.96356 | AM33: =AL33+'Planning Model'!K39+'Planning Model'!K47+'Planning Model'!K94+'Planning Model'!K102-'Planning Model'!K148 -> 154.84979 | AN33: =AM33+'Planning Model'!L39+'Planning Model'!L47+'Planning Model'!L94+'Planning Model'!L102-'Planning Model'!L148 -> 140.37428 | ... AX33: =AW33+'Planning Model'!V39+'Planning Model'!V47+'Planning Model'!V94+'Planning Model'!V102-'Planning Model'!V148 -> 45.230547
A34: SW | B34: CRTH | C34: SONH | D34: 50 | E34: 115 | F34: 0 | G34: 0 | H34: 0 | I34: 0 | J34: 0 | K34: 0 | L34: 0 | M34: 0 | N34: 0 | O34: 0 | P34: 20.292352 | Q34: 215.208 | R34: 395.7954 | S34: 0 | T34: 0 | U34: 0 | V34: 0 | W34: =D34*SUM(E34:V34) -> 37314.788 | AB34: HW | AC34: SCST | AF34: 0 | AG34: =AF34-'Planning Model'!E151 -> 0 | AH34: =AG34-'Planning Model'!F151 -> 0 | AI34: =AH34-'Planning Model'!G151 -> 0 | AJ34: =AI34-'Planning Model'!H151 -> 0 | AK34: =AJ34-'Planning Model'!I151 -> 0 | AL34: =AK34-'Planning Model'!J151 -> 0 | AM34: =AL34-'Planning Model'!K151 -> 0 | AN34: =AM34-'Planning Model'!L151 -> 0 | ... AX34: =AW34-'Planning Model'!V151 -> 0
A35: HW | B35: HASS | C35: CJER | D35: 141.66667 | E35: 113.4 | F35: 0 | G35: 0 | H35: 0 | I35: 0 | J35: 0 | K35: 0 | L35: 0 | M35: 0 | N35: 0 | O35: 0 | P35: 0 | Q35: 0 | R35: 0 | S35: 0 | T35: 0 | U35: 0 | V35: 0 | W35: =D35*SUM(E35:V35) -> 16065 | AB35: HW | AC35: SEMA | AF35: 0 | AG35: =AF35+'Planning Model'!E40+'Planning Model'!E95-'Planning Model'!E154 -> 0 | AH35: =AG35+'Planning Model'!F40+'Planning Model'!F95-'Planning Model'!F154 -> 0 | AI35: =AH35+'Planning Model'!G40+'Planning Model'!G95-'Planning Model'!G154 -> 0 | AJ35: =AI35+'Planning Model'!H40+'Planning Model'!H95-'Planning Model'!H154 -> 92.405332 | AK35: =AJ35+'Planning Model'!I40+'Planning Model'!I95-'Planning Model'!I154 -> 145.64832 | AL35: =AK35+'Planning Model'!J40+'Planning Model'!J95-'Planning Model'!J154 -> 126.1663 | AM35: =AL35+'Planning Model'!K40+'Planning Model'!K95-'Planning Model'!K154 -> 4.194349 | AN35: =AM35+'Planning Model'!L40+'Planning Model'!L95-'Planning Model'!L154 -> -8.0000001e-06 | ... AX35: =AW35+'Planning Model'!V40+'Planning Model'!V95-'Planning Model'!V154 -> -1.7e-05
A36: HW | B36: HASS | C36: HUDV | D36: 161.66667 | E36: 0 | F36: 0 | G36: 0 | H36: 0 | I36: 0 | J36: 0 | K36: 0 | L36: 0 | M36: 0 | N36: 0 | O36: 0 | P36: 0 | Q36: 0 | R36: 0 | S36: 0 | T36: 0 | U36: 0 | V36: 0 | W36: =D36*SUM(E36:V36) -> 0 | AB36: HW | AC36: SONH | AF36: 0 | AG36: =AF36+'Planning Model'!E44+'Planning Model'!E99-'Planning Model'!E157 -> 105.825 | AH36: =AG36+'Planning Model'!F44+'Planning Model'!F99-'Planning Model'!F157 -> 292.88514 | AI36: =AH36+'Planning Model'!G44+'Planning Model'!G99-'Planning Model'!G157 -> 512.88514 | AJ36: =AI36+'Planning Model'!H44+'Planning Model'!H99-'Planning Model'!H157 -> 473.0481 | AK36: =AJ36+'Planning Model'!I44+'Planning Model'!I99-'Planning Model'!I157 -> 166.97983 | AL36: =AK36+'Planning Model'!J44+'Planning Model'!J99-'Planning Model'!J157 -> 293.72251 | AM36: =AL36+'Planning Model'!K44+'Planning Model'!K99-'Planning Model'!K157 -> 1.4e-05 | AN36: =AM36+'Planning Model'!L44+'Planning Model'!L99-'Planning Model'!L157 -> 1.4e-05 | ... AX36: =AW36+'Planning Model'!V44+'Planning Model'!V99-'Planning Model'!V157 -> 1.4e-05
A37: HW | B37: HASS | C37: NCMA | D37: 175 | E37: 0 | F37: 0 | G37: 0 | H37: 0 | I37: 0 | J37: 48.7333 | K37: 114.166 | L37: 27.842203 | M37: 0 | N37: 77.5656 | O37: 77.5656 | P37: 62.05248 | Q37: 75.83625 | R37: 0 | S37: 102.86755 | T37: 98.759131 | U37: 191.41942 | V37: 184.743 | W37: =D37*SUM(E37:V37) -> 185771.34 | AB37: HW | AC37: UVLY | AF37: 0 | AG37: =AF37+'Planning Model'!E45+'Planning Model'!E100-'Planning Model'!E155-'Planning Model'!E149-'Planning Model'!E144-'Planning Model'!E158 -> 0 | AH37: =AG37+'Planning Model'!F45+'Planning Model'!F100-'Planning Model'!F155-'Planning Model'!F149-'Planning Model'!F144-'Planning Model'!F158 -> 0 | AI37: =AH37+'Planning Model'!G45+'Planning Model'!G100-'Planning Model'!G155-'Planning Model'!G149-'Planning Model'!G144-'Planning Model'!G158 -> 0 | AJ37: =AI37+'Planning Model'!H45+'Planning Model'!H100-'Planning Model'!H155-'Planning Model'!H149-'Planning Model'!H144-'Planning Model'!H158 -> 0 | AK37: =AJ37+'Planning Model'!I45+'Planning Model'!I100-'Planning Model'!I155-'Planning Model'!I149-'Planning Model'!I144-'Planning Model'!I158 -> 0 | AL37: =AK37+'Planning Model'!J45+'Planning Model'!J100-'Planning Model'!J155-'Planning Model'!J149-'Planning Model'!J144-'Planning Model'!J158 -> 0 | AM37: =AL37+'Planning Model'!K45+'Planning Model'!K100-'Planning Model'!K155-'Planning Model'!K149-'Planning Model'!K144-'Planning Model'!K158 -> 74.96656 | AN37: =AM37+'Planning Model'!L45+'Planning Model'!L100-'Planning Model'!L155-'Planning Model'!L149-'Planning Model'!L144-'Planning Model'!L158 -> 10.97494 | ... AX37: =AW37+'Planning Model'!V45+'Planning Model'!V100-'Planning Model'!V155-'Planning Model'!V149-'Planning Model'!V144-'Planning Model'!V158 -> -4e-06
A38: HW | B38: HASS | C38: NJER | D38: 150 | E38: 0 | F38: 0 | G38: 0 | H38: 0 | I38: 19.8733 | J38: 26.838 | K38: 31.66695 | L38: 41.28705 | M38: 17.79435 | N38: 11.91645 | O38: 11.91645 | P38: 9.53316 | Q38: 4.96125 | R38: 12.16215 | S38: 27.1593 | T38: 26.946675 | U38: 33.580575 | V38: 40.257 | W38: =D38*SUM(E38:V38) -> 47383.899 | AB38: HW | AC38: WTCT | AF38: 800 | AG38: =AF38+'Planning Model'!E41+'Planning Model'!E65+'Planning Model'!E96+'Planning Model'!E120-'Planning Model'!E161 -> 794.33 | AH38: =AG38+'Planning Model'!F41+'Planning Model'!F65+'Planning Model'!F96+'Planning Model'!F120-'Planning Model'!F161 -> 742.17734 | AI38: =AH38+'Planning Model'!G41+'Planning Model'!G65+'Planning Model'!G96+'Planning Model'!G120-'Planning Model'!G161 -> 665.31482 | AJ38: =AI38+'Planning Model'!H41+'Planning Model'!H65+'Planning Model'!H96+'Planning Model'!H120-'Planning Model'!H161 -> 568.18772 | AK38: =AJ38+'Planning Model'!I41+'Planning Model'!I65+'Planning Model'!I96+'Planning Model'!I120-'Planning Model'!I161 -> 413.49878 | AL38: =AK38+'Planning Model'!J41+'Planning Model'!J65+'Planning Model'!J96+'Planning Model'!J120-'Planning Model'!J161 -> 232.81856 | AM38: =AL38+'Planning Model'!K41+'Planning Model'!K65+'Planning Model'!K96+'Planning Model'!K120-'Planning Model'!K161 -> 29.60576 | AN38: =AM38+'Planning Model'!L41+'Planning Model'!L65+'Planning Model'!L96+'Planning Model'!L120-'Planning Model'!L161 -> 0 | ... AX38: =AW38+'Planning Model'!V41+'Planning Model'!V65+'Planning Model'!V96+'Planning Model'!V120-'Planning Model'!V161 -> 0
A39: HW | B39: HASS | C39: OHIO | D39: 75 | E39: 0 | F39: 0 | G39: 0 | H39: 0 | I39: 0 | J39: 0 | K39: 0 | L39: 0 | M39: 0 | N39: 0 | O39: 0 | P39: 0 | Q39: 0 | R39: 0 | S39: 0 | T39: 0 | U39: 0 | V39: 0 | W39: =D39*SUM(E39:V39) -> 0 | AB39: HW | AC39: WTMA | AF39: 3000 | AG39: =AF39+'Planning Model'!E42+'Planning Model'!E46+'Planning Model'!E48+'Planning Model'!E66+'Planning Model'!E97+'Planning Model'!E101+'Planning Model'!E103+'Planning Model'!E121-'Planning Model'!E136-'Planning Model'!E141-'Planning Model'!E145-'Planning Model'!E150-'Planning Model'!E153-'Planning Model'!E156-'Planning Model'!E160-'Planning Model'!E162 -> 2924.3055 | AH39: =AG39+'Planning Model'!F42+'Planning Model'!F46+'Planning Model'!F48+'Planning Model'!F66+'Planning Model'!F97+'Planning Model'!F101+'Planning Model'!F103+'Planning Model'!F121-'Planning Model'!F136-'Planning Model'!F141-'Planning Model'!F145-'Planning Model'!F150-'Planning Model'!F153-'Planning Model'!F156-'Planning Model'!F160-'Planning Model'!F162 -> 2755.9028 | AI39: =AH39+'Planning Model'!G42+'Planning Model'!G46+'Planning Model'!G48+'Planning Model'!G66+'Planning Model'!G97+'Planning Model'!G101+'Planning Model'!G103+'Planning Model'!G121-'Planning Model'!G136-'Planning Model'!G141-'Planning Model'!G145-'Planning Model'!G150-'Planning Model'!G153-'Planning Model'!G156-'Planning Model'!G160-'Planning Model'!G162 -> 2405.8654 | AJ39: =AI39+'Planning Model'!H42+'Planning Model'!H46+'Planning Model'!H48+'Planning Model'!H66+'Planning Model'!H97+'Planning Model'!H101+'Planning Model'!H103+'Planning Model'!H121-'Planning Model'!H136-'Planning Model'!H141-'Planning Model'!H145-'Planning Model'!H150-'Planning Model'!H153-'Planning Model'!H156-'Planning Model'!H160-'Planning Model'!H162 -> 1917.3646 | AK39: =AJ39+'Planning Model'!I42+'Planning Model'!I46+'Planning Model'!I48+'Planning Model'!I66+'Planning Model'!I97+'Planning Model'!I101+'Planning Model'!I103+'Planning Model'!I121-'Planning Model'!I136-'Planning Model'!I141-'Planning Model'!I145-'Planning Model'!I150-'Planning Model'!I153-'Planning Model'!I156-'Planning Model'!I160-'Planning Model'!I162 -> 1568.1154 | AL39: =AK39+'Planning Model'!J42+'Planning Model'!J46+'Planning Model'!J48+'Planning Model'!J66+'Planning Model'!J97+'Planning Model'!J101+'Planning Model'!J103+'Planning Model'!J121-'Planning Model'!J136-'Planning Model'!J141-'Planning Model'!J145-'Planning Model'!J150-'Planning Model'!J153-'Planning Model'!J156-'Planning Model'!J160-'Planning Model'!J162 -> 903.16624 | AM39: =AL39+'Planning Model'!K42+'Planning Model'!K46+'Planning Model'!K48+'Planning Model'!K66+'Planning Model'!K97+'Planning Model'!K101+'Planning Model'!K103+'Planning Model'!K121-'Planning Model'!K136-'Planning Model'!K141-'Planning Model'!K145-'Planning Model'!K150-'Planning Model'!K153-'Planning Model'!K156-'Planning Model'!K160-'Planning Model'!K162 -> 617.42384 | AN39: =AM39+'Planning Model'!L42+'Planning Model'!L46+'Planning Model'!L48+'Planning Model'!L66+'Planning Model'!L97+'Planning Model'!L101+'Planning Model'!L103+'Planning Model'!L121-'Planning Model'!L136-'Planning Model'!L141-'Planning Model'!L145-'Planning Model'!L150-'Planning Model'!L153-'Planning Model'!L156-'Planning Model'!L160-'Planning Model'!L162 -> 88.23149 | ... AX39: =AW39+'Planning Model'!V42+'Planning Model'!V46+'Planning Model'!V48+'Planning Model'!V66+'Planning Model'!V97+'Planning Model'!V101+'Planning Model'!V103+'Planning Model'!V121-'Planning Model'!V136-'Planning Model'!V141-'Planning Model'!V145-'Planning Model'!V150-'Planning Model'!V153-'Planning Model'!V156-'Planning Model'!V160-'Planning Model'!V162 -> -2.0000004e-06
A40: HW | B40: HASS | C40: SEMA | D40: 156.66667 | E40: 12.474 | F40: 40.652482 | G40: 62.333145 | H40: 171.14037 | I40: 205.1267 | J40: 149.4287 | K40: 79.167047 | L40: 34.983367 | M40: 62.715558 | N40: 128.66975 | O40: 94.83003 | P40: 120.86402 | Q40: 135.6975 | R40: 212.83785 | S40: 94.973155 | T40: 99.294194 | U40: 0 | V40: 0 | W40: =D40*SUM(E40:V40) -> 267146.1 | AB40: SW | AC40: BERK | AF40: 50 | AG40: =AF40+'Planning Model'!E49+'Planning Model'!E104-'Planning Model'!E164 -> 50 | AH40: =AG40+'Planning Model'!F49+'Planning Model'!F104-'Planning Model'!F164 -> 50 | AI40: =AH40+'Planning Model'!G49+'Planning Model'!G104-'Planning Model'!G164 -> 50 | AJ40: =AI40+'Planning Model'!H49+'Planning Model'!H104-'Planning Model'!H164 -> 50 | AK40: =AJ40+'Planning Model'!I49+'Planning Model'!I104-'Planning Model'!I164 -> 0 | AL40: =AK40+'Planning Model'!J49+'Planning Model'!J104-'Planning Model'!J164 -> 0 | AM40: =AL40+'Planning Model'!K49+'Planning Model'!K104-'Planning Model'!K164 -> 0 | AN40: =AM40+'Planning Model'!L49+'Planning Model'!L104-'Planning Model'!L164 -> 0 | ... AX40: =AW40+'Planning Model'!V49+'Planning Model'!V104-'Planning Model'!V164 -> 0
A41: HW | B41: HASS | C41: WTCT | D41: 171.66667 | E41: 0 | F41: 0 | G41: 0 | H41: 0 | I41: 0 | J41: 0 | K41: 0 | L41: 120.88738 | M41: 62.484326 | N41: 6.8482012 | O41: 40.68792 | P41: 32.550336 | Q41: 8.505 | R41: 0 | S41: 0 | T41: 0 | U41: 0 | V41: 0 | W41: =D41*SUM(E41:V41) -> 46687.01 | AB41: SW | AC41: CJER | AF41: 0 | AG41: =AF41+'Planning Model'!E26+'Planning Model'!E50+'Planning Model'!E81+'Planning Model'!E105-'Planning Model'!E165 -> 816.48 | AH41: =AG41+'Planning Model'!F26+'Planning Model'!F50+'Planning Model'!F81+'Planning Model'!F105-'Planning Model'!F165 -> 816.48 | AI41: =AH41+'Planning Model'!G26+'Planning Model'!G50+'Planning Model'!G81+'Planning Model'!G105-'Planning Model'!G165 -> 816.48 | AJ41: =AI41+'Planning Model'!H26+'Planning Model'!H50+'Planning Model'!H81+'Planning Model'!H105-'Planning Model'!H165 -> 790.965 | AK41: =AJ41+'Planning Model'!I26+'Planning Model'!I50+'Planning Model'!I81+'Planning Model'!I105-'Planning Model'!I165 -> 748.44 | AL41: =AK41+'Planning Model'!J26+'Planning Model'!J50+'Planning Model'!J81+'Planning Model'!J105-'Planning Model'!J165 -> 697.41 | AM41: =AL41+'Planning Model'!K26+'Planning Model'!K50+'Planning Model'!K81+'Planning Model'!K105-'Planning Model'!K165 -> 612.36 | AN41: =AM41+'Planning Model'!L26+'Planning Model'!L50+'Planning Model'!L81+'Planning Model'!L105-'Planning Model'!L165 -> 484.785 | ... AX41: =AW41+'Planning Model'!V26+'Planning Model'!V50+'Planning Model'!V81+'Planning Model'!V105-'Planning Model'!V165 -> 1.2079227e-13
A42: HW | B42: HASS | C42: WTMA | D42: 170 | E42: 0 | F42: 0 | G42: 0 | H42: 0 | I42: 0 | J42: 0 | K42: 0 | L42: 0 | M42: 0 | N42: 0 | O42: 0 | P42: 0 | Q42: 0 | R42: 0 | S42: 0 | T42: 0 | U42: 0 | V42: 0 | W42: =D42*SUM(E42:V42) -> 0 | AB42: SW | AC42: CTRI | AF42: 75 | AG42: =AF42+'Planning Model'!E51+'Planning Model'!E67+'Planning Model'!E106+'Planning Model'!E122-'Planning Model'!E166-'Planning Model'!E170-'Planning Model'!E179-'Planning Model'!E186 -> 5.9205 | AH42: =AG42+'Planning Model'!F51+'Planning Model'!F67+'Planning Model'!F106+'Planning Model'!F122-'Planning Model'!F166-'Planning Model'!F170-'Planning Model'!F179-'Planning Model'!F186 -> 0 | AI42: =AH42+'Planning Model'!G51+'Planning Model'!G67+'Planning Model'!G106+'Planning Model'!G122-'Planning Model'!G166-'Planning Model'!G170-'Planning Model'!G179-'Planning Model'!G186 -> 0 | AJ42: =AI42+'Planning Model'!H51+'Planning Model'!H67+'Planning Model'!H106+'Planning Model'!H122-'Planning Model'!H166-'Planning Model'!H170-'Planning Model'!H179-'Planning Model'!H186 -> 0 | AK42: =AJ42+'Planning Model'!I51+'Planning Model'!I67+'Planning Model'!I106+'Planning Model'!I122-'Planning Model'!I166-'Planning Model'!I170-'Planning Model'!I179-'Planning Model'!I186 -> 0 | AL42: =AK42+'Planning Model'!J51+'Planning Model'!J67+'Planning Model'!J106+'Planning Model'!J122-'Planning Model'!J166-'Planning Model'!J170-'Planning Model'!J179-'Planning Model'!J186 -> 0 | AM42: =AL42+'Planning Model'!K51+'Planning Model'!K67+'Planning Model'!K106+'Planning Model'!K122-'Planning Model'!K166-'Planning Model'!K170-'Planning Model'!K179-'Planning Model'!K186 -> 0 | AN42: =AM42+'Planning Model'!L51+'Planning Model'!L67+'Planning Model'!L106+'Planning Model'!L122-'Planning Model'!L166-'Planning Model'!L170-'Planning Model'!L179-'Planning Model'!L186 -> 0 | ... AX42: =AW42+'Planning Model'!V51+'Planning Model'!V67+'Planning Model'!V106+'Planning Model'!V122-'Planning Model'!V166-'Planning Model'!V170-'Planning Model'!V179-'Planning Model'!V186 -> 4e-05
A43: HW | B43: JAFF | C43: BERK | D43: 41.666667 | E43: 0 | F43: 0 | G43: 0 | H43: 0 | I43: 0 | J43: 0 | K43: 0 | L43: 0 | M43: 0 | N43: 0 | O43: 0 | P43: 0 | Q43: 0 | R43: 0 | S43: 0 | T43: 0 | U43: 0 | V43: 0 | W43: =D43*SUM(E43:V43) -> 0 | AB43: SW | AC43: DEME | AF43: 150 | AG43: =AF43+'Planning Model'!E30+'Planning Model'!E52+'Planning Model'!E68+'Planning Model'!E85+'Planning Model'!E107+'Planning Model'!E123-'Planning Model'!E167 -> 95.757 | AH43: =AG43+'Planning Model'!F30+'Planning Model'!F52+'Planning Model'!F68+'Planning Model'!F85+'Planning Model'!F107+'Planning Model'!F123-'Planning Model'!F167 -> 17.22372 | AI43: =AH43+'Planning Model'!G30+'Planning Model'!G52+'Planning Model'!G68+'Planning Model'!G85+'Planning Model'!G107+'Planning Model'!G123-'Planning Model'!G167 -> 147.65864 | AJ43: =AI43+'Planning Model'!H30+'Planning Model'!H52+'Planning Model'!H68+'Planning Model'!H85+'Planning Model'!H107+'Planning Model'!H123-'Planning Model'!H167 -> 183.08336 | AK43: =AJ43+'Planning Model'!I30+'Planning Model'!I52+'Planning Model'!I68+'Planning Model'!I85+'Planning Model'!I107+'Planning Model'!I123-'Planning Model'!I167 -> 130.5408 | AL43: =AK43+'Planning Model'!J30+'Planning Model'!J52+'Planning Model'!J68+'Planning Model'!J85+'Planning Model'!J107+'Planning Model'!J123-'Planning Model'!J167 -> 5.732974 | AM43: =AL43+'Planning Model'!K30+'Planning Model'!K52+'Planning Model'!K68+'Planning Model'!K85+'Planning Model'!K107+'Planning Model'!K123-'Planning Model'!K167 -> 4e-06 | AN43: =AM43+'Planning Model'!L30+'Planning Model'!L52+'Planning Model'!L68+'Planning Model'!L85+'Planning Model'!L107+'Planning Model'!L123-'Planning Model'!L167 -> 4e-06 | ... AX43: =AW43+'Planning Model'!V30+'Planning Model'!V52+'Planning Model'!V68+'Planning Model'!V85+'Planning Model'!V107+'Planning Model'!V123-'Planning Model'!V167 -> 2e-06
A44: HW | B44: JAFF | C44: SONH | D44: 33.333333 | E44: 105.825 | F44: 187.06014 | G44: 220 | H44: 115.49056 | I44: 130.1872 | J44: 126.74268 | K44: 39.273764 | L44: 0 | M44: 0 | N44: 0 | O44: 0 | P44: 0 | Q44: 301.68375 | R44: 440 | S44: 440 | T44: 440 | U44: 305.2808 | V44: 400.11401 | W44: =D44*SUM(E44:V44) -> 108388.6 | AB44: SW | AC44: HUDV | AF44: 500 | AG44: =AF44+'Planning Model'!E27+'Planning Model'!E53+'Planning Model'!E69+'Planning Model'!E82+'Planning Model'!E108+'Planning Model'!E124-'Planning Model'!E169 -> 292.46 | AH44: =AG44+'Planning Model'!F27+'Planning Model'!F53+'Planning Model'!F69+'Planning Model'!F82+'Planning Model'!F108+'Planning Model'!F124-'Planning Model'!F169 -> 853.73489 | AI44: =AH44+'Planning Model'!G27+'Planning Model'!G53+'Planning Model'!G69+'Planning Model'!G82+'Planning Model'!G108+'Planning Model'!G124-'Planning Model'!G169 -> 949.11315 | AJ44: =AI44+'Planning Model'!H27+'Planning Model'!H53+'Planning Model'!H69+'Planning Model'!H82+'Planning Model'!H108+'Planning Model'!H124-'Planning Model'!H169 -> 1096.9726 | AK44: =AJ44+'Planning Model'!I27+'Planning Model'!I53+'Planning Model'!I69+'Planning Model'!I82+'Planning Model'!I108+'Planning Model'!I124-'Planning Model'!I169 -> 842.45852 | AL44: =AK44+'Planning Model'!J27+'Planning Model'!J53+'Planning Model'!J69+'Planning Model'!J82+'Planning Model'!J108+'Planning Model'!J124-'Planning Model'!J169 -> 77.0138 | AM44: =AL44+'Planning Model'!K27+'Planning Model'!K53+'Planning Model'!K69+'Planning Model'!K82+'Planning Model'!K108+'Planning Model'!K124-'Planning Model'!K169 -> -1e-05 | AN44: =AM44+'Planning Model'!L27+'Planning Model'!L53+'Planning Model'!L69+'Planning Model'!L82+'Planning Model'!L108+'Planning Model'!L124-'Planning Model'!L169 -> -1e-05 | ... AX44: =AW44+'Planning Model'!V27+'Planning Model'!V53+'Planning Model'!V69+'Planning Model'!V82+'Planning Model'!V108+'Planning Model'!V124-'Planning Model'!V169 -> -4e-05
A45: HW | B45: JAFF | C45: UVLY | D45: 33.333333 | E45: 14.175 | F45: 32.939865 | G45: 0 | H45: 104.50944 | I45: 89.8128 | J45: 93.257325 | K45: 180.72624 | L45: 0 | M45: 0 | N45: 0 | O45: 0 | P45: 0 | Q45: 21.2625 | R45: 0 | S45: 0 | T45: 0 | U45: 134.7192 | V45: 39.885987 | W45: =D45*SUM(E45:V45) -> 23709.612 | AB45: SW | AC45: NCMA | AF45: 500 | AG45: =AF45+'Planning Model'!E31+'Planning Model'!E54+'Planning Model'!E70+'Planning Model'!E86+'Planning Model'!E109+'Planning Model'!E125-'Planning Model'!E173 -> 297.77 | AH45: =AG45+'Planning Model'!F31+'Planning Model'!F54+'Planning Model'!F70+'Planning Model'!F86+'Planning Model'!F109+'Planning Model'!F125-'Planning Model'!F173 -> 555.67795 | AI45: =AH45+'Planning Model'!G31+'Planning Model'!G54+'Planning Model'!G70+'Planning Model'!G86+'Planning Model'!G109+'Planning Model'!G125-'Planning Model'!G173 -> 991.94985 | AJ45: =AI45+'Planning Model'!H31+'Planning Model'!H54+'Planning Model'!H70+'Planning Model'!H86+'Planning Model'!H109+'Planning Model'!H125-'Planning Model'!H173 -> -4.4e-05 | AK45: =AJ45+'Planning Model'!I31+'Planning Model'!I54+'Planning Model'!I70+'Planning Model'!I86+'Planning Model'!I109+'Planning Model'!I125-'Planning Model'!I173 -> -4.4e-05 | AL45: =AK45+'Planning Model'!J31+'Planning Model'!J54+'Planning Model'!J70+'Planning Model'!J86+'Planning Model'!J109+'Planning Model'!J125-'Planning Model'!J173 -> -4.4e-05 | AM45: =AL45+'Planning Model'!K31+'Planning Model'!K54+'Planning Model'!K70+'Planning Model'!K86+'Planning Model'!K109+'Planning Model'!K125-'Planning Model'!K173 -> -4.4e-05 | AN45: =AM45+'Planning Model'!L31+'Planning Model'!L54+'Planning Model'!L70+'Planning Model'!L86+'Planning Model'!L109+'Planning Model'!L125-'Planning Model'!L173 -> -4.4e-05 | ... AX45: =AW45+'Planning Model'!V31+'Planning Model'!V54+'Planning Model'!V70+'Planning Model'!V86+'Planning Model'!V109+'Planning Model'!V125-'Planning Model'!V173 -> -3.4e-05
A46: HW | B46: JAFF | C46: WTMA | D46: 50 | E46: 0 | F46: 0 | G46: 0 | H46: 0 | I46: 0 | J46: 0 | K46: 0 | L46: 0 | M46: 0 | N46: 0 | O46: 0 | P46: 0 | Q46: 0 | R46: 0 | S46: 0 | T46: 0 | U46: 0 | V46: 0 | W46: =D46*SUM(E46:V46) -> 0 | AB46: SW | AC46: NJER | AF46: 200 | AG46: =AF46+'Planning Model'!E28+'Planning Model'!E83-'Planning Model'!E174 -> 170.2325 | AH46: =AG46+'Planning Model'!F28+'Planning Model'!F83-'Planning Model'!F174 -> 97.2596 | AI46: =AH46+'Planning Model'!G28+'Planning Model'!G83-'Planning Model'!G174 -> 161.68005 | AJ46: =AI46+'Planning Model'!H28+'Planning Model'!H83-'Planning Model'!H174 -> 0 | AK46: =AJ46+'Planning Model'!I28+'Planning Model'!I83-'Planning Model'!I174 -> 0 | AL46: =AK46+'Planning Model'!J28+'Planning Model'!J83-'Planning Model'!J174 -> 0 | AM46: =AL46+'Planning Model'!K28+'Planning Model'!K83-'Planning Model'!K174 -> 0 | AN46: =AM46+'Planning Model'!L28+'Planning Model'!L83-'Planning Model'!L174 -> 0 | ... AX46: =AW46+'Planning Model'!V28+'Planning Model'!V83-'Planning Model'!V174 -> 1e-05
A47: HW | B47: MICH | C47: OHIO | D47: 66.666667 | E47: 0 | F47: 0 | G47: 0 | H47: 0 | I47: 0 | J47: 0 | K47: 0 | L47: 0 | M47: 0 | N47: 0 | O47: 0 | P47: 0 | Q47: 0 | R47: 0 | S47: 0 | T47: 0 | U47: 0 | V47: 0 | W47: =D47*SUM(E47:V47) -> 0 | AB47: SW | AC47: OHIO | AF47: 0 | AG47: =AF47+'Planning Model'!E71+'Planning Model'!E126-'Planning Model'!E175 -> 0 | AH47: =AG47+'Planning Model'!F71+'Planning Model'!F126-'Planning Model'!F175 -> 0 | AI47: =AH47+'Planning Model'!G71+'Planning Model'!G126-'Planning Model'!G175 -> 0 | AJ47: =AI47+'Planning Model'!H71+'Planning Model'!H126-'Planning Model'!H175 -> 0 | AK47: =AJ47+'Planning Model'!I71+'Planning Model'!I126-'Planning Model'!I175 -> 0 | AL47: =AK47+'Planning Model'!J71+'Planning Model'!J126-'Planning Model'!J175 -> 0 | AM47: =AL47+'Planning Model'!K71+'Planning Model'!K126-'Planning Model'!K175 -> 0 | AN47: =AM47+'Planning Model'!L71+'Planning Model'!L126-'Planning Model'!L175 -> 0 | ... AX47: =AW47+'Planning Model'!V71+'Planning Model'!V126-'Planning Model'!V175 -> 0
A48: HW | B48: MICH | C48: WTMA | D48: 66.666667 | E48: 0 | F48: 80 | G48: 90 | H48: 90 | I48: 90 | J48: 90 | K48: 90 | L48: 90 | M48: 116.99878 | N48: 344.88909 | O48: 231.36152 | P48: 241.58587 | Q48: 360 | R48: 360 | S48: 360 | T48: 360 | U48: 360 | V48: 360 | W48: =D48*SUM(E48:V48) -> 247655.68 | AB48: SW | AC48: SCST | AF48: 150 | AG48: =AF48+'Planning Model'!E32+'Planning Model'!E87-'Planning Model'!E178 -> 83.472 | AH48: =AG48+'Planning Model'!F32+'Planning Model'!F87-'Planning Model'!F178 -> 0 | AI48: =AH48+'Planning Model'!G32+'Planning Model'!G87-'Planning Model'!G178 -> 0 | AJ48: =AI48+'Planning Model'!H32+'Planning Model'!H87-'Planning Model'!H178 -> 0 | AK48: =AJ48+'Planning Model'!I32+'Planning Model'!I87-'Planning Model'!I178 -> 0 | AL48: =AK48+'Planning Model'!J32+'Planning Model'!J87-'Planning Model'!J178 -> 0 | AM48: =AL48+'Planning Model'!K32+'Planning Model'!K87-'Planning Model'!K178 -> 0 | AN48: =AM48+'Planning Model'!L32+'Planning Model'!L87-'Planning Model'!L178 -> 0 | ... AX48: =AW48+'Planning Model'!V32+'Planning Model'!V87-'Planning Model'!V178 -> 0
A49: SW | B49: PRIN | C49: BERK | D49: 183.33333 | E49: 0 | F49: 0 | G49: 0 | H49: 0 | I49: 283.24208 | J49: 412.29051 | K49: 450 | L49: 450 | M49: 0 | N49: 0 | O49: 0 | P49: 0 | Q49: 0 | R49: 311.58599 | S49: 452.95504 | T49: 727.94295 | U49: 634.36669 | V49: 0 | W49: =D49*SUM(E49:V49) -> 682436.93 | AB49: SW | AC49: SEMA | AF49: 0 | AG49: =AF49+'Planning Model'!E33+'Planning Model'!E55+'Planning Model'!E88+'Planning Model'!E110-'Planning Model'!E181 -> 0 | AH49: =AG49+'Planning Model'!F33+'Planning Model'!F55+'Planning Model'!F88+'Planning Model'!F110-'Planning Model'!F181 -> 0 | AI49: =AH49+'Planning Model'!G33+'Planning Model'!G55+'Planning Model'!G88+'Planning Model'!G110-'Planning Model'!G181 -> 0 | AJ49: =AI49+'Planning Model'!H33+'Planning Model'!H55+'Planning Model'!H88+'Planning Model'!H110-'Planning Model'!H181 -> 0 | AK49: =AJ49+'Planning Model'!I33+'Planning Model'!I55+'Planning Model'!I88+'Planning Model'!I110-'Planning Model'!I181 -> 0 | AL49: =AK49+'Planning Model'!J33+'Planning Model'!J55+'Planning Model'!J88+'Planning Model'!J110-'Planning Model'!J181 -> 0 | AM49: =AL49+'Planning Model'!K33+'Planning Model'!K55+'Planning Model'!K88+'Planning Model'!K110-'Planning Model'!K181 -> 0 | AN49: =AM49+'Planning Model'!L33+'Planning Model'!L55+'Planning Model'!L88+'Planning Model'!L110-'Planning Model'!L181 -> 0 | ... AX49: =AW49+'Planning Model'!V33+'Planning Model'!V55+'Planning Model'!V88+'Planning Model'!V110-'Planning Model'!V181 -> 0
A50: SW | B50: PRIN | C50: CJER | D50: 216.66667 | E50: 0 | F50: 0 | G50: 0 | H50: 0 | I50: 0 | J50: 0 | K50: 0 | L50: 0 | M50: 0 | N50: 0 | O50: 0 | P50: 0 | Q50: 0 | R50: 0 | S50: 0 | T50: 0 | U50: 0 | V50: 0 | W50: =D50*SUM(E50:V50) -> 0 | AB50: SW | AC50: SONH | AF50: 500 | AG50: =AF50+'Planning Model'!E34+'Planning Model'!E56+'Planning Model'!E72+'Planning Model'!E89+'Planning Model'!E111+'Planning Model'!E127-'Planning Model'!E184 -> 615 | AH50: =AG50+'Planning Model'!F34+'Planning Model'!F56+'Planning Model'!F72+'Planning Model'!F89+'Planning Model'!F111+'Planning Model'!F127-'Planning Model'!F184 -> 615 | AI50: =AH50+'Planning Model'!G34+'Planning Model'!G56+'Planning Model'!G72+'Planning Model'!G89+'Planning Model'!G111+'Planning Model'!G127-'Planning Model'!G184 -> 615 | AJ50: =AI50+'Planning Model'!H34+'Planning Model'!H56+'Planning Model'!H72+'Planning Model'!H89+'Planning Model'!H111+'Planning Model'!H127-'Planning Model'!H184 -> 615 | AK50: =AJ50+'Planning Model'!I34+'Planning Model'!I56+'Planning Model'!I72+'Planning Model'!I89+'Planning Model'!I111+'Planning Model'!I127-'Planning Model'!I184 -> 334.8536 | AL50: =AK50+'Planning Model'!J34+'Planning Model'!J56+'Planning Model'!J72+'Planning Model'!J89+'Planning Model'!J111+'Planning Model'!J127-'Planning Model'!J184 -> 0 | AM50: =AL50+'Planning Model'!K34+'Planning Model'!K56+'Planning Model'!K72+'Planning Model'!K89+'Planning Model'!K111+'Planning Model'!K127-'Planning Model'!K184 -> 0 | AN50: =AM50+'Planning Model'!L34+'Planning Model'!L56+'Planning Model'!L72+'Planning Model'!L89+'Planning Model'!L111+'Planning Model'!L127-'Planning Model'!L184 -> 0 | ... AX50: =AW50+'Planning Model'!V34+'Planning Model'!V56+'Planning Model'!V72+'Planning Model'!V89+'Planning Model'!V111+'Planning Model'!V127-'Planning Model'!V184 -> 2e-06
A51: SW | B51: PRIN | C51: CTRI | D51: 190 | E51: 0 | F51: 0 | G51: 0 | H51: 0 | I51: 0 | J51: 0 | K51: 0 | L51: 0 | M51: 0 | N51: 0 | O51: 0 | P51: 0 | Q51: 0 | R51: 0 | S51: 0 | T51: 0 | U51: 0 | V51: 319.08728 | W51: =D51*SUM(E51:V51) -> 60626.583 | AB51: SW | AC51: UVLY | AF51: 75 | AG51: =AF51+'Planning Model'!E57+'Planning Model'!E73+'Planning Model'!E112+'Planning Model'!E128-'Planning Model'!E171-'Planning Model'!E176-'Planning Model'!E182-'Planning Model'!E185 -> 0 | AH51: =AG51+'Planning Model'!F57+'Planning Model'!F73+'Planning Model'!F112+'Planning Model'!F128-'Planning Model'!F171-'Planning Model'!F176-'Planning Model'!F182-'Planning Model'!F185 -> 5e-06 | AI51: =AH51+'Planning Model'!G57+'Planning Model'!G73+'Planning Model'!G112+'Planning Model'!G128-'Planning Model'!G171-'Planning Model'!G176-'Planning Model'!G182-'Planning Model'!G185 -> -1.5e-05 | AJ51: =AI51+'Planning Model'!H57+'Planning Model'!H73+'Planning Model'!H112+'Planning Model'!H128-'Planning Model'!H171-'Planning Model'!H176-'Planning Model'!H182-'Planning Model'!H185 -> -1.5e-05 | AK51: =AJ51+'Planning Model'!I57+'Planning Model'!I73+'Planning Model'!I112+'Planning Model'!I128-'Planning Model'!I171-'Planning Model'!I176-'Planning Model'!I182-'Planning Model'!I185 -> -4.5e-05 | AL51: =AK51+'Planning Model'!J57+'Planning Model'!J73+'Planning Model'!J112+'Planning Model'!J128-'Planning Model'!J171-'Planning Model'!J176-'Planning Model'!J182-'Planning Model'!J185 -> -9.5e-05 | AM51: =AL51+'Planning Model'!K57+'Planning Model'!K73+'Planning Model'!K112+'Planning Model'!K128-'Planning Model'!K171-'Planning Model'!K176-'Planning Model'!K182-'Planning Model'!K185 -> -9.5e-05 | AN51: =AM51+'Planning Model'!L57+'Planning Model'!L73+'Planning Model'!L112+'Planning Model'!L128-'Planning Model'!L171-'Planning Model'!L176-'Planning Model'!L182-'Planning Model'!L185 -> -9.5e-05 | ... AX51: =AW51+'Planning Model'!V57+'Planning Model'!V73+'Planning Model'!V112+'Planning Model'!V128-'Planning Model'!V171-'Planning Model'!V176-'Planning Model'!V182-'Planning Model'!V185 -> -1.4000001e-05
A52: SW | B52: PRIN | C52: DEME | D52: 186.66667 | E52: 0 | F52: 0 | G52: 350 | H52: 450 | I52: 166.75792 | J52: 37.709494 | K52: 0 | L52: 0 | M52: 0 | N52: 0 | O52: 0 | P52: 0 | Q52: 0 | R52: 0 | S52: 35.458972 | T52: 172.05705 | U52: 265.63331 | V52: 0 | W52: =D52*SUM(E52:V52) -> 275821.79 | AB52: SW | AC52: WTCT | AF52: 0 | AG52: =AF52+'Planning Model'!E29+'Planning Model'!E58+'Planning Model'!E74+'Planning Model'!E84+'Planning Model'!E113+'Planning Model'!E129-'Planning Model'!E188 -> 0 | AH52: =AG52+'Planning Model'!F29+'Planning Model'!F58+'Planning Model'!F74+'Planning Model'!F84+'Planning Model'!F113+'Planning Model'!F129-'Planning Model'!F188 -> 257.82266 | AI52: =AH52+'Planning Model'!G29+'Planning Model'!G58+'Planning Model'!G74+'Planning Model'!G84+'Planning Model'!G113+'Planning Model'!G129-'Planning Model'!G188 -> 334.68518 | AJ52: =AI52+'Planning Model'!H29+'Planning Model'!H58+'Planning Model'!H74+'Planning Model'!H84+'Planning Model'!H113+'Planning Model'!H129-'Planning Model'!H188 -> 431.81228 | AK52: =AJ52+'Planning Model'!I29+'Planning Model'!I58+'Planning Model'!I74+'Planning Model'!I84+'Planning Model'!I113+'Planning Model'!I129-'Planning Model'!I188 -> 57.86226 | AL52: =AK52+'Planning Model'!J29+'Planning Model'!J58+'Planning Model'!J74+'Planning Model'!J84+'Planning Model'!J113+'Planning Model'!J129-'Planning Model'!J188 -> -2e-05 | AM52: =AL52+'Planning Model'!K29+'Planning Model'!K58+'Planning Model'!K74+'Planning Model'!K84+'Planning Model'!K113+'Planning Model'!K129-'Planning Model'!K188 -> -2e-05 | AN52: =AM52+'Planning Model'!L29+'Planning Model'!L58+'Planning Model'!L74+'Planning Model'!L84+'Planning Model'!L113+'Planning Model'!L129-'Planning Model'!L188 -> -9.9999999e-06 | ... AX52: =AW52+'Planning Model'!V29+'Planning Model'!V58+'Planning Model'!V74+'Planning Model'!V84+'Planning Model'!V113+'Planning Model'!V129-'Planning Model'!V188 -> -4.8e-05
A53: SW | B53: PRIN | C53: HUDV | D53: 233.33333 | E53: 0 | F53: 0 | G53: 0 | H53: 0 | I53: 0 | J53: 0 | K53: 0 | L53: 0 | M53: 0 | N53: 0 | O53: 0 | P53: 0 | Q53: 0 | R53: 0 | S53: 0 | T53: 0 | U53: 0 | V53: 0 | W53: =D53*SUM(E53:V53) -> 0 | AB53: SW | AC53: WTMA | AF53: 0 | AG53: =AF53+'Planning Model'!E59+'Planning Model'!E75+'Planning Model'!E130-'Planning Model'!E163-'Planning Model'!E168-'Planning Model'!E172-'Planning Model'!E177-'Planning Model'!E180-'Planning Model'!E183-'Planning Model'!E187-'Planning Model'!E189 -> 2642.8515 | AH53: =AG53+'Planning Model'!F59+'Planning Model'!F75+'Planning Model'!F130-'Planning Model'!F163-'Planning Model'!F168-'Planning Model'!F172-'Planning Model'!F177-'Planning Model'!F180-'Planning Model'!F183-'Planning Model'!F187-'Planning Model'!F189 -> 4244.0972 | AI53: =AH53+'Planning Model'!G59+'Planning Model'!G75+'Planning Model'!G130-'Planning Model'!G163-'Planning Model'!G168-'Planning Model'!G172-'Planning Model'!G177-'Planning Model'!G180-'Planning Model'!G183-'Planning Model'!G187-'Planning Model'!G189 -> 4594.1345 | AJ53: =AI53+'Planning Model'!H59+'Planning Model'!H75+'Planning Model'!H130-'Planning Model'!H163-'Planning Model'!H168-'Planning Model'!H172-'Planning Model'!H177-'Planning Model'!H180-'Planning Model'!H183-'Planning Model'!H187-'Planning Model'!H189 -> 4409.1419 | AK53: =AJ53+'Planning Model'!I59+'Planning Model'!I75+'Planning Model'!I130-'Planning Model'!I163-'Planning Model'!I168-'Planning Model'!I172-'Planning Model'!I177-'Planning Model'!I180-'Planning Model'!I183-'Planning Model'!I187-'Planning Model'!I189 -> 3203.3083 | AL53: =AK53+'Planning Model'!J59+'Planning Model'!J75+'Planning Model'!J130-'Planning Model'!J163-'Planning Model'!J168-'Planning Model'!J172-'Planning Model'!J177-'Planning Model'!J180-'Planning Model'!J183-'Planning Model'!J187-'Planning Model'!J189 -> 1937.3027 | AM53: =AL53+'Planning Model'!K59+'Planning Model'!K75+'Planning Model'!K130-'Planning Model'!K163-'Planning Model'!K168-'Planning Model'!K172-'Planning Model'!K177-'Planning Model'!K180-'Planning Model'!K183-'Planning Model'!K187-'Planning Model'!K189 -> 470.75285 | AN53: =AM53+'Planning Model'!L59+'Planning Model'!L75+'Planning Model'!L130-'Planning Model'!L163-'Planning Model'!L168-'Planning Model'!L172-'Planning Model'!L177-'Planning Model'!L180-'Planning Model'!L183-'Planning Model'!L187-'Planning Model'!L189 -> -5.6e-05 | ... AX53: =AW53+'Planning Model'!V59+'Planning Model'!V75+'Planning Model'!V130-'Planning Model'!V163-'Planning Model'!V168-'Planning Model'!V172-'Planning Model'!V177-'Planning Model'!V180-'Planning Model'!V183-'Planning Model'!V187-'Planning Model'!V189 -> 2.4e-05
A54: SW | B54: PRIN | C54: NCMA | D54: 216.66667 | E54: 0 | F54: 0 | G54: 0 | H54: 0 | I54: 0 | J54: 0 | K54: 0 | L54: 0 | M54: 0 | N54: 0 | O54: 0 | P54: 0 | Q54: 0 | R54: 0 | S54: 0 | T54: 0 | U54: 0 | V54: 0 | W54: =D54*SUM(E54:V54) -> 0
A55: SW | B55: PRIN | C55: SEMA | D55: 216.66667 | E55: 0 | F55: 0 | G55: 0 | H55: 0 | I55: 0 | J55: 0 | K55: 0 | L55: 0 | M55: 0 | N55: 0 | O55: 0 | P55: 0 | Q55: 0 | R55: 0 | S55: 0 | T55: 0 | U55: 0 | V55: 0 | W55: =D55*SUM(E55:V55) -> 0
A56: SW | B56: PRIN | C56: SONH | D56: 221.66667 | E56: 0 | F56: 0 | G56: 0 | H56: 0 | I56: 0 | J56: 0 | K56: 0 | L56: 0 | M56: 0 | N56: 0 | O56: 0 | P56: 0 | Q56: 0 | R56: 0 | S56: 0 | T56: 0 | U56: 0 | V56: 0 | W56: =D56*SUM(E56:V56) -> 0 | AB56: Combined Inventory at depot storage points
A57: SW | B57: PRIN | C57: UVLY | D57: 178.33333 | E57: 0 | F57: 0 | G57: 0 | H57: 0 | I57: 0 | J57: 0 | K57: 0 | L57: 0 | M57: 0 | N57: 0 | O57: 0 | P57: 0 | Q57: 0 | R57: 0 | S57: 0 | T57: 0 | U57: 0 | V57: 0 | W57: =D57*SUM(E57:V57) -> 0 | AC57: regionID | AD57: Capacity | AE57: Cost/Mo | AF57: 44236 | AG57: Mar 21 | AH57: Apr 21 | AI57: May 21 | AJ57: Jun 21 | AK57: Jul 21 | AL57: Aug 21 | AM57: Sep 21 | AN57: Oct 21 | AO57: Nov 21 | AP57: Dec 21 | AQ57: Jan 22 | AR57: Feb 22 | AS57: Mar 22 | AT57: Apr 22 | AU57: May 22 | AV57: Jun 22 | AW57: Jul 22 | AX57: Aug 22 | AY57: Total Cost
A58: SW | B58: PRIN | C58: WTCT | D58: 191.66667 | E58: 0 | F58: 0 | G58: 0 | H58: 0 | I58: 0 | J58: 0 | K58: 0 | L58: 0 | M58: 0 | N58: 0 | O58: 0 | P58: 0 | Q58: 0 | R58: 0 | S58: 0 | T58: 0 | U58: 0 | V58: 580.91272 | W58: =D58*SUM(E58:V58) -> 111341.6 | AC58: BERK | AD58: 1000 | AE58: 1 | AF58: =AF26+AF40 -> 350 | AG58: =AG26+AG40 -> 334.17531 | AH58: =AH26+AH40 -> 864.93398 | AI58: =AI26+AI40 -> 999.99999 | AJ58: =AJ26+AJ40 -> 838.23489 | AK58: =AK26+AK40 -> 647.26452 | AL58: =AL26+AL40 -> 509.83435 | AM58: =AM26+AM40 -> 296.97546 | ... AX58: =AX26+AX40 -> -1.6999999e-06 | AY58: =AE58*SUM(AG58:AX58) -> 5232.0905
A59: SW | B59: PRIN | C59: WTMA | D59: 186.66667 | E59: 0 | F59: 0 | G59: 0 | H59: 0 | I59: 0 | J59: 0 | K59: 0 | L59: 0 | M59: 0 | N59: 0 | O59: 0 | P59: 0 | Q59: 0 | R59: 0 | S59: 0 | T59: 0 | U59: 0 | V59: 0 | W59: =D59*SUM(E59:V59) -> 0 | AC59: CJER | AD59: 1000 | AE59: 0.16666667 | AF59: =AF27+AF41 -> 0 | AG59: =AG27+AG41 -> 926.1 | AH59: =AH27+AH41 -> 922.32 | AI59: =AI27+AI41 -> 916.65 | AJ59: =AJ27+AJ41 -> 888.3 | AK59: =AK27+AK41 -> 841.05 | AL59: =AL27+AL41 -> 784.35 | AM59: =AM27+AM41 -> 689.85 | ... AX59: =AX27+AX41 -> 1.3367085e-13 | AY59: =AE59*SUM(AG59:AX59) -> 1307.25
A60: HW | B60: SCHY | C60: BERK | D60: 55 | E60: 30.952813 | F60: 600 | G60: 235.72269 | H60: 0 | I60: 0 | J60: 0 | K60: 0 | L60: 0 | M60: 6.2703063 | N60: 135.20399 | O60: 0 | P60: 0 | Q60: 0 | R60: 103.862 | S60: 487.77772 | T60: 100.45379 | U60: 16.856709 | V60: 206.14525 | W60: =D60*SUM(E60:V60) -> 105778.49 | AC60: CTRI | AD60: 1250 | AE60: 5 | AF60: =AF28+AF42 -> 75 | AG60: =AG28+AG42 -> 5.9205 | AH60: =AH28+AH42 -> 0 | AI60: =AI28+AI42 -> 0 | AJ60: =AJ28+AJ42 -> 0 | AK60: =AK28+AK42 -> 0 | AL60: =AL28+AL42 -> 0 | AM60: =AM28+AM42 -> 0 | ... AX60: =AX28+AX42 -> 4e-05 | AY60: =AE60*SUM(AG60:AX60) -> 29.6027
A61: HW | B61: SCHY | C61: CJER | D61: 58.333333 | E61: 0 | F61: 0 | G61: 0 | H61: 0 | I61: 0 | J61: 0 | K61: 0 | L61: 0 | M61: 0 | N61: 0 | O61: 0 | P61: 0 | Q61: 0 | R61: 0 | S61: 0 | T61: 0 | U61: 0 | V61: 0 | W61: =D61*SUM(E61:V61) -> 0 | AC61: DEME | AD61: 500 | AE61: 0.8 | AF61: =AF29+AF43 -> 150 | AG61: =AG29+AG43 -> 95.757 | AH61: =AH29+AH43 -> 17.22372 | AI61: =AI29+AI43 -> 147.65864 | AJ61: =AJ29+AJ43 -> 183.08336 | AK61: =AK29+AK43 -> 130.5408 | AL61: =AL29+AL43 -> 5.732974 | AM61: =AM29+AM43 -> 4e-06 | ... AX61: =AX29+AX43 -> 2e-06 | AY61: =AE61*SUM(AG61:AX61) -> 773.73612
A62: HW | B62: SCHY | C62: HUDV | D62: 50 | E62: 469.04719 | F62: 0 | G62: 0 | H62: 0 | I62: 91.380906 | J62: 0 | K62: 30.770103 | L62: 48.736503 | M62: 90.3231 | N62: 180.9563 | O62: 0 | P62: 0 | Q62: 0 | R62: 259.20051 | S62: 0 | T62: 221.78914 | U62: 278.7434 | V62: 180.0351 | W62: =D62*SUM(E62:V62) -> 92549.113 | AC62: HUDV | AD62: 1500 | AE62: 0.8 | AF62: =AF30+AF44 -> 800 | AG62: =AG30+AG44 -> 1016.1472 | AH62: =AH30+AH44 -> 1500 | AI62: =AI30+AI44 -> 1500 | AJ62: =AJ30+AJ44 -> 1500 | AK62: =AK30+AK44 -> 1151.0379 | AL62: =AL30+AL44 -> 198.90314 | AM62: =AM30+AM44 -> 2.0000001e-06 | ... AX62: =AX30+AX44 -> -2.1e-05 | AY62: =AE62*SUM(AG62:AX62) -> 10728.069
A63: HW | B63: SCHY | C63: NCMA | D63: 66.666667 | E63: 0 | F63: 0 | G63: 114.27731 | H63: 350 | I63: 258.61909 | J63: 350 | K63: 319.2299 | L63: 301.2635 | M63: 152.0694 | N63: 0 | O63: 0 | P63: 0 | Q63: 0 | R63: 192.7233 | S63: 162.91371 | T63: 282.06642 | U63: 222.36648 | V63: 43.749296 | W63: =D63*SUM(E63:V63) -> 183285.23 | AC63: NCMA | AD63: 1000 | AE63: 2 | AF63: =AF31+AF45 -> 750 | AG63: =AG31+AG45 -> 497.2125 | AH63: =AH31+AH45 -> 626.63825 | AI63: =AI31+AI45 -> 999.99996 | AJ63: =AJ31+AJ45 -> 104.16637 | AK63: =AK31+AK45 -> -4.4e-05 | AL63: =AL31+AL45 -> -4.4e-05 | AM63: =AM31+AM45 -> -4.4e-05 | ... AX63: =AX31+AX45 -> -2.4e-05 | AY63: =AE63*SUM(AG63:AX63) -> 6456.0331
A64: HW | B64: SCHY | C64: NJER | D64: 50 | E64: 0 | F64: 0 | G64: 0 | H64: 0 | I64: 0 | J64: 0 | K64: 0 | L64: 0 | M64: 0 | N64: 0 | O64: 0 | P64: 0 | Q64: 0 | R64: 0 | S64: 0 | T64: 0 | U64: 0 | V64: 0 | W64: =D64*SUM(E64:V64) -> 0 | AC64: NJER | AD64: 1000 | AE64: 3 | AF64: =AF32+AF46 -> 250 | AG64: =AG32+AG46 -> 216.925 | AH64: =AH32+AH46 -> 135.844 | AI64: =AI32+AI46 -> 182.15825 | AJ64: =AJ32+AJ46 -> 2.51375 | AK64: =AK32+AK46 -> 0 | AL64: =AL32+AL46 -> 0 | AM64: =AM32+AM46 -> 0 | ... AX64: =AX32+AX46 -> 1e-05 | AY64: =AE64*SUM(AG64:AX64) -> 1614.3475
A65: HW | B65: SCHY | C65: WTCT | D65: 63.333333 | E65: 0 | F65: 0 | G65: 0 | H65: 0 | I65: 0 | J65: 0 | K65: 0 | L65: 0 | M65: 1.3371938 | N65: 33.839719 | O65: 0 | P65: 0 | Q65: 0 | R65: 94.214197 | S65: 99.308573 | T65: 145.69065 | U65: 232.03341 | V65: 271.02033 | W65: =D65*SUM(E65:V65) -> 55571.458 | AC65: OHIO | AD65: 1200 | AE65: 4.5 | AF65: =AF33+AF47 -> 200 | AG65: =AG33+AG47 -> 195.1805 | AH65: =AH33+AH47 -> 189.80534 | AI65: =AI33+AI47 -> 185.56985 | AJ65: =AJ33+AJ47 -> 180.10113 | AK65: =AK33+AK47 -> 172.33607 | AL65: =AL33+AL47 -> 162.96356 | AM65: =AM33+AM47 -> 154.84979 | ... AX65: =AX33+AX47 -> 45.230547 | AY65: =AE65*SUM(AG65:AX65) -> 10206.331
A66: HW | B66: SCHY | C66: WTMA | D66: 60 | E66: 0 | F66: 0 | G66: 0 | H66: 0 | I66: 0 | J66: 0 | K66: 0 | L66: 0 | M66: 0 | N66: 0 | O66: 0 | P66: 0 | Q66: 0 | R66: 0 | S66: 0 | T66: 0 | U66: 0 | V66: 49.050022 | W66: =D66*SUM(E66:V66) -> 2943.0013 | AC66: SCST | AD66: 500 | AE66: 4 | AF66: =AF34+AF48 -> 150 | AG66: =AG34+AG48 -> 83.472 | AH66: =AH34+AH48 -> 0 | AI66: =AI34+AI48 -> 0 | AJ66: =AJ34+AJ48 -> 0 | AK66: =AK34+AK48 -> 0 | AL66: =AL34+AL48 -> 0 | AM66: =AM34+AM48 -> 0 | ... AX66: =AX34+AX48 -> 0 | AY66: =AE66*SUM(AG66:AX66) -> 2333.888
A67: SW | B67: STFC | C67: CTRI | D67: 83.333333 | E67: 0 | F67: 167.64576 | G67: 251.12808 | H67: 357.99246 | I67: 548.65188 | J67: 738.09036 | K67: 610.91982 | L67: 456.05322 | M67: 220.15476 | N67: 126.65646 | O67: 126.65646 | P67: 101.32517 | Q67: 103.61925 | R67: 260.34939 | S67: 376.69212 | T67: 536.98869 | U67: 822.97782 | V67: 0 | W67: =D67*SUM(E67:V67) -> 483825.14 | AC67: SEMA | AD67: 500 | AE67: 0.5 | AF67: =AF35+AF49 -> 0 | AG67: =AG35+AG49 -> 0 | AH67: =AH35+AH49 -> 0 | AI67: =AI35+AI49 -> 0 | AJ67: =AJ35+AJ49 -> 92.405332 | AK67: =AK35+AK49 -> 145.64832 | AL67: =AL35+AL49 -> 126.1663 | AM67: =AM35+AM49 -> 4.194349 | ... AX67: =AX35+AX49 -> -1.7e-05 | AY67: =AE67*SUM(AG67:AX67) -> 1455.9873
A68: SW | B68: STFC | C68: DEME | D68: 100 | E68: 0 | F68: 0 | G68: 0 | H68: 0 | I68: 0 | J68: 0 | K68: 0 | L68: 0 | M68: 0 | N68: 0 | O68: 0 | P68: 0 | Q68: 0 | R68: 0 | S68: 0 | T68: 0 | U68: 0 | V68: 0 | W68: =D68*SUM(E68:V68) -> 0 | AC68: SONH | AD68: 2000 | AE68: 1 | AF68: =AF36+AF50 -> 500 | AG68: =AG36+AG50 -> 720.825 | AH68: =AH36+AH50 -> 907.88514 | AI68: =AI36+AI50 -> 1127.8851 | AJ68: =AJ36+AJ50 -> 1088.0481 | AK68: =AK36+AK50 -> 501.83343 | AL68: =AL36+AL50 -> 293.72251 | AM68: =AM36+AM50 -> 1.4e-05 | ... AX68: =AX36+AX50 -> 1.6e-05 | AY68: =AE68*SUM(AG68:AX68) -> 8907.9737
A69: SW | B69: STFC | C69: HUDV | D69: 133.33333 | E69: 0 | F69: 0 | G69: 0 | H69: 0 | I69: 0 | J69: 0 | K69: 0 | L69: 0 | M69: 0 | N69: 0 | O69: 0 | P69: 0 | Q69: 0 | R69: 0 | S69: 0 | T69: 0 | U69: 0 | V69: 0 | W69: =D69*SUM(E69:V69) -> 0 | AC69: UVLY | AD69: 2500 | AE69: 4.5 | AF69: =AF37+AF51 -> 75 | AG69: =AG37+AG51 -> 0 | AH69: =AH37+AH51 -> 5e-06 | AI69: =AI37+AI51 -> -1.5e-05 | AJ69: =AJ37+AJ51 -> -1.5e-05 | AK69: =AK37+AK51 -> -4.5e-05 | AL69: =AL37+AL51 -> -9.5e-05 | AM69: =AM37+AM51 -> 74.966465 | ... AX69: =AX37+AX51 -> -1.8000001e-05 | AY69: =AE69*SUM(AG69:AX69) -> 546.93326
... A71: SW | B71: STFC | C71: OHIO | D71: 133.33333 | E71: 0 | F71: 0 | G71: 0 | H71: 0 | I71: 0 | J71: 0 | K71: 0 | L71: 0 | M71: 0 | N71: 0 | O71: 0 | P71: 0 | Q71: 0 | R71: 0 | S71: 0 | T71: 0 | U71: 0 | V71: 0 | W71: =D71*SUM(E71:V71) -> 0 | AC71: WTMA | AD71: 7000 | AE71: 1 | AF71: =AF39+AF53 -> 3000 | AG71: =AG39+AG53 -> 5567.157 | AH71: =AH39+AH53 -> 7000 | AI71: =AI39+AI53 -> 7000 | AJ71: =AJ39+AJ53 -> 6326.5065 | AK71: =AK39+AK53 -> 4771.4237 | AL71: =AL39+AL53 -> 2840.4689 | AM71: =AM39+AM53 -> 1088.1767 | ... AX71: =AX39+AX53 -> 2.2e-05 | AY71: =AE71*SUM(AG71:AX71) -> 47586.457
A72: SW | B72: STFC | C72: SONH | D72: 115 | E72: 0 | F72: 0 | G72: 0 | H72: 0 | I72: 0 | J72: 0 | K72: 0 | L72: 0 | M72: 0 | N72: 0 | O72: 0 | P72: 0 | Q72: 0 | R72: 0 | S72: 0 | T72: 0 | U72: 0 | V72: 0 | W72: =D72*SUM(E72:V72) -> 0
A73: SW | B73: STFC | C73: UVLY | D73: 68.333333 | E73: 70.53 | F73: 381.87213 | G73: 1122.5576 | H73: 2079.1575 | I73: 2133.8529 | J73: 1666.9764 | K73: 1030.8985 | L73: 1348.7942 | M73: 577.11497 | N73: 659.23106 | O73: 394.33338 | P73: 315.4667 | Q73: 218.295 | R73: 115.28953 | S73: 382.71828 | T73: 1637.431 | U73: 2000.3092 | V73: 2101.5388 | W73: =D73*SUM(E73:V73) -> 1246151.8
A74: SW | B74: STFC | C74: WTCT | D74: 86.666667 | E74: 32.13 | F74: 553.3544 | G74: 375.64811 | H74: 633.2435 | I74: 502.62064 | J74: 0 | K74: 624.59807 | L74: 421.29093 | M74: 0 | N74: 0 | O74: 0 | P74: 141.33563 | Q74: 48.195 | R74: 1427.3124 | S74: 669.31663 | T74: 825.58035 | U74: 0 | V74: 0 | W74: =D74*SUM(E74:V74) -> 542067.56
A75: SW | B75: STFC | C75: WTMA | D75: 78.333333 | E75: 2897.34 | F75: 2125.291 | G75: 1105.6442 | H75: 906.02163 | I75: 0 | J75: 0 | K75: 0 | L75: 457.43885 | M75: 594.45267 | N75: 481.65091 | O75: 481.65091 | P75: 385.32073 | Q75: 644.18363 | R75: 1603.9676 | S75: 2571.273 | T75: 0 | U75: 0 | V75: 0 | W75: =D75*SUM(E75:V75) -> 1116581.8
A79: Flow from buffer locations to depot storage points
B80: SourceID | C80: StorID | D80: Cost/ton | E80: Mar 21 | F80: Apr 21 | G80: May 21 | H80: Jun 21 | I80: Jul 21 | J80: Aug 21 | K80: Sep 21 | L80: Oct 21 | M80: Nov 21 | N80: Dec 21 | O80: Jan 22 | P80: Feb 22 | Q80: Mar 22 | R80: Apr 22 | S80: May 22 | T80: Jun 22 | U80: Jul 22 | V80: Aug 22 | W80: Total Cost
B81: ARGT | C81: CJER | D81: 58.666667 | E81: 0 | F81: 0 | G81: 0 | H81: 0 | I81: 0 | J81: 0 | K81: 0 | L81: 0 | M81: 0 | N81: 0 | O81: 0 | P81: 0 | Q81: 0 | R81: 0 | S81: 0 | T81: 0 | U81: 0 | V81: 0 | W81: =D81*SUM(E81:V81) -> 0 | AB81: Storage capacity
B82: ARGT | C82: HUDV | D82: 42 | E82: 0 | F82: 0 | G82: 0 | H82: 0 | I82: 0 | J82: 0 | K82: 0 | L82: 0 | M82: 0 | N82: 0 | O82: 0 | P82: 0 | Q82: 0 | R82: 0 | S82: 0 | T82: 0 | U82: 0 | V82: 100 | W82: =D82*SUM(E82:V82) -> 4200 | AC82: SourceID | AG82: Mar 21 | AH82: Apr 21 | AI82: May 21 | AJ82: Jun 21 | AK82: Jul 21 | AL82: Aug 21 | AM82: Sep 21 | AN82: Oct 21 | AO82: Nov 21 | AP82: Dec 21 | AQ82: Jan 22 | AR82: Feb 22 | AS82: Mar 22 | AT82: Apr 22 | AU82: May 22 | AV82: Jun 22 | AW82: Jul 22 | AX82: Aug 22
B83: ARGT | C83: NJER | D83: 42 | E83: 0 | F83: 0 | G83: 0 | H83: 0 | I83: 0 | J83: 0 | K83: 0 | L83: 0 | M83: 0 | N83: 0 | O83: 0 | P83: 0 | Q83: 0 | R83: 0 | S83: 0 | T83: 0 | U83: 0 | V83: 0 | W83: =D83*SUM(E83:V83) -> 0 | AC83: ARGT | AG83: =$AD13 -> 100 | AH83: =$AD13 -> 100 | AI83: =$AD13 -> 100 | AJ83: =$AD13 -> 100 | AK83: =$AD13 -> 100 | AL83: =$AD13 -> 100 | AM83: =$AD13 -> 100 | AN83: =$AD13 -> 100 | ... AX83: =$AD13 -> 100
B84: ARGT | C84: WTCT | D84: 50.333333 | E84: 0 | F84: 0 | G84: 0 | H84: 0 | I84: 0 | J84: 0 | K84: 100 | L84: 0 | M84: 0 | N84: 0 | O84: 0 | P84: 0 | Q84: 0 | R84: 0 | S84: 0 | T84: 0 | U84: 0 | V84: 0 | W84: =D84*SUM(E84:V84) -> 5033.3333 | AC84: CRTH | AG84: =$AD14 -> 200 | AH84: =$AD14 -> 200 | AI84: =$AD14 -> 200 | AJ84: =$AD14 -> 200 | AK84: =$AD14 -> 200 | AL84: =$AD14 -> 200 | AM84: =$AD14 -> 200 | AN84: =$AD14 -> 200 | ... AX84: =$AD14 -> 200
B85: CRTH | C85: DEME | D85: 41.833333 | E85: 0 | F85: 0 | G85: 0 | H85: 0 | I85: 0 | J85: 0 | K85: 0 | L85: 0 | M85: 0 | N85: 0 | O85: 0 | P85: 0 | Q85: 0 | R85: 0 | S85: 0 | T85: 0 | U85: 0 | V85: 0 | W85: =D85*SUM(E85:V85) -> 0 | AC85: HASS | AG85: =$AD15 -> 500 | AH85: =$AD15 -> 500 | AI85: =$AD15 -> 500 | AJ85: =$AD15 -> 500 | AK85: =$AD15 -> 500 | AL85: =$AD15 -> 500 | AM85: =$AD15 -> 500 | AN85: =$AD15 -> 500 | ... AX85: =$AD15 -> 500
B86: CRTH | C86: NCMA | D86: 58.5 | E86: 0 | F86: 0 | G86: 0 | H86: 0 | I86: 0 | J86: 0 | K86: 0 | L86: 0 | M86: 0 | N86: 0 | O86: 0 | P86: 0 | Q86: 0 | R86: 0 | S86: 0 | T86: 0 | U86: 0 | V86: 0 | W86: =D86*SUM(E86:V86) -> 0 | AC86: JAFF | AG86: =$AD16 -> 100 | AH86: =$AD16 -> 100 | AI86: =$AD16 -> 100 | AJ86: =$AD16 -> 100 | AK86: =$AD16 -> 100 | AL86: =$AD16 -> 100 | AM86: =$AD16 -> 100 | AN86: =$AD16 -> 100 | ... AX86: =$AD16 -> 100
B87: CRTH | C87: SCST | D87: 50.166667 | E87: 0 | F87: 0 | G87: 0 | H87: 0 | I87: 0 | J87: 0 | K87: 0 | L87: 200 | M87: 0 | N87: 0 | O87: 0 | P87: 0 | Q87: 0 | R87: 0 | S87: 0 | T87: 0 | U87: 0 | V87: 200 | W87: =D87*SUM(E87:V87) -> 20066.667 | AC87: MICH | AG87: =$AD17 -> 100 | AH87: =$AD17 -> 100 | AI87: =$AD17 -> 100 | AJ87: =$AD17 -> 100 | AK87: =$AD17 -> 100 | AL87: =$AD17 -> 100 | AM87: =$AD17 -> 100 | AN87: =$AD17 -> 100 | ... AX87: =$AD17 -> 100
B88: CRTH | C88: SEMA | D88: 66.833333 | E88: 0 | F88: 0 | G88: 0 | H88: 0 | I88: 0 | J88: 0 | K88: 0 | L88: 0 | M88: 0 | N88: 0 | O88: 0 | P88: 0 | Q88: 0 | R88: 0 | S88: 0 | T88: 0 | U88: 0 | V88: 0 | W88: =D88*SUM(E88:V88) -> 0 | AC88: PRIN | AG88: =$AD18 -> 1000 | AH88: =$AD18 -> 1000 | AI88: =$AD18 -> 1000 | AJ88: =$AD18 -> 1000 | AK88: =$AD18 -> 1000 | AL88: =$AD18 -> 1000 | AM88: =$AD18 -> 1000 | AN88: =$AD18 -> 1000 | ... AX88: =$AD18 -> 1000
B89: CRTH | C89: SONH | D89: 50.166667 | E89: 0 | F89: 0 | G89: 0 | H89: 0 | I89: 0 | J89: 0 | K89: 0 | L89: 0 | M89: 0 | N89: 0 | O89: 0 | P89: 0 | Q89: 0 | R89: 0 | S89: 0 | T89: 0 | U89: 0 | V89: 0 | W89: =D89*SUM(E89:V89) -> 0 | AC89: SCHY | AG89: =$AD19 -> 100 | AH89: =$AD19 -> 100 | AI89: =$AD19 -> 100 | AJ89: =$AD19 -> 100 | AK89: =$AD19 -> 100 | AL89: =$AD19 -> 100 | AM89: =$AD19 -> 100 | AN89: =$AD19 -> 100 | ... AX89: =$AD19 -> 100
B90: HASS | C90: CJER | D90: 141.83333 | E90: 0 | F90: 0 | G90: 0 | H90: 0 | I90: 0 | J90: 0 | K90: 0 | L90: 0 | M90: 0 | N90: 0 | O90: 0 | P90: 0 | Q90: 0 | R90: 0 | S90: 0 | T90: 0 | U90: 0 | V90: 0 | W90: =D90*SUM(E90:V90) -> 0 | AC90: STFC | AG90: =$AD20 -> 1000 | AH90: =$AD20 -> 1000 | AI90: =$AD20 -> 1000 | AJ90: =$AD20 -> 1000 | AK90: =$AD20 -> 1000 | AL90: =$AD20 -> 1000 | AM90: =$AD20 -> 1000 | AN90: =$AD20 -> 1000 | ... AX90: =$AD20 -> 1000
B91: HASS | C91: HUDV | D91: 161.83333 | E91: 0 | F91: 0 | G91: 0 | H91: 0 | I91: 0 | J91: 0 | K91: 0 | L91: 0 | M91: 0 | N91: 0 | O91: 0 | P91: 0 | Q91: 0 | R91: 0 | S91: 0 | T91: 0 | U91: 0 | V91: 0 | W91: =D91*SUM(E91:V91) -> 0
B92: HASS | C92: NCMA | D92: 175.16667 | E92: 0 | F92: 0 | G92: 0 | H92: 0 | I92: 0 | J92: 0 | K92: 0 | L92: 0 | M92: 0 | N92: 0 | O92: 0 | P92: 0 | Q92: 0 | R92: 0 | S92: 0 | T92: 0 | U92: 130.39235 | V92: 369.60765 | W92: =D92*SUM(E92:V92) -> 87583.333
B93: HASS | C93: NJER | D93: 150.16667 | E93: 0 | F93: 0 | G93: 0 | H93: 0 | I93: 0 | J93: 0 | K93: 0 | L93: 0 | M93: 0 | N93: 0 | O93: 0 | P93: 0 | Q93: 0 | R93: 0 | S93: 0 | T93: 0 | U93: 0 | V93: 0 | W93: =D93*SUM(E93:V93) -> 0 | AB93: Storage capacity
B94: HASS | C94: OHIO | D94: 75.166667 | E94: 0 | F94: 0 | G94: 0 | H94: 0 | I94: 0 | J94: 0 | K94: 0 | L94: 0 | M94: 0 | N94: 0 | O94: 0 | P94: 0 | Q94: 0 | R94: 0 | S94: 0 | T94: 0 | U94: 0 | V94: 0 | W94: =D94*SUM(E94:V94) -> 0 | AC94: regionID | AG94: Mar 21 | AH94: Apr 21 | AI94: May 21 | AJ94: Jun 21 | AK94: Jul 21 | AL94: Aug 21 | AM94: Sep 21 | AN94: Oct 21 | AO94: Nov 21 | AP94: Dec 21 | AQ94: Jan 22 | AR94: Feb 22 | AS94: Mar 22 | AT94: Apr 22 | AU94: May 22 | AV94: Jun 22 | AW94: Jul 22 | AX94: Aug 22
B95: HASS | C95: SEMA | D95: 156.83333 | E95: 0 | F95: 0 | G95: 0 | H95: 0 | I95: 0 | J95: 0 | K95: 0 | L95: 82.005766 | M95: 0 | N95: 0 | O95: 0 | P95: 0 | Q95: 0 | R95: 0 | S95: 0 | T95: 0 | U95: 0 | V95: 0 | W95: =D95*SUM(E95:V95) -> 12861.238 | AC95: BERK | AG95: =$AD58 -> 1000 | AH95: =$AD58 -> 1000 | AI95: =$AD58 -> 1000 | AJ95: =$AD58 -> 1000 | AK95: =$AD58 -> 1000 | AL95: =$AD58 -> 1000 | AM95: =$AD58 -> 1000 | AN95: =$AD58 -> 1000 | ... AX95: =$AD58 -> 1000
B96: HASS | C96: WTCT | D96: 171.83333 | E96: 0 | F96: 0 | G96: 0 | H96: 0 | I96: 0 | J96: 0 | K96: 0 | L96: 0 | M96: 0 | N96: 0 | O96: 0 | P96: 0 | Q96: 0 | R96: 0 | S96: 0 | T96: 0 | U96: 0 | V96: 0 | W96: =D96*SUM(E96:V96) -> 0 | AC96: CJER | AG96: =$AD59 -> 1000 | AH96: =$AD59 -> 1000 | AI96: =$AD59 -> 1000 | AJ96: =$AD59 -> 1000 | AK96: =$AD59 -> 1000 | AL96: =$AD59 -> 1000 | AM96: =$AD59 -> 1000 | AN96: =$AD59 -> 1000 | ... AX96: =$AD59 -> 1000
B97: HASS | C97: WTMA | D97: 170.16667 | E97: 0 | F97: 0 | G97: 0 | H97: 0 | I97: 0 | J97: 0 | K97: 0 | L97: 0 | M97: 0 | N97: 0 | O97: 0 | P97: 0 | Q97: 0 | R97: 0 | S97: 0 | T97: 0 | U97: 0 | V97: 0 | W97: =D97*SUM(E97:V97) -> 0 | AC97: CTRI | AG97: =$AD60 -> 1250 | AH97: =$AD60 -> 1250 | AI97: =$AD60 -> 1250 | AJ97: =$AD60 -> 1250 | AK97: =$AD60 -> 1250 | AL97: =$AD60 -> 1250 | AM97: =$AD60 -> 1250 | AN97: =$AD60 -> 1250 | ... AX97: =$AD60 -> 1250
B98: JAFF | C98: BERK | D98: 42 | E98: 0 | F98: 0 | G98: 0 | H98: 0 | I98: 0 | J98: 0 | K98: 0 | L98: 0 | M98: 0 | N98: 0 | O98: 0 | P98: 0 | Q98: 0 | R98: 0 | S98: 0 | T98: 0 | U98: 0 | V98: 0 | W98: =D98*SUM(E98:V98) -> 0 | AC98: DEME | AG98: =$AD61 -> 500 | AH98: =$AD61 -> 500 | AI98: =$AD61 -> 500 | AJ98: =$AD61 -> 500 | AK98: =$AD61 -> 500 | AL98: =$AD61 -> 500 | AM98: =$AD61 -> 500 | AN98: =$AD61 -> 500 | ... AX98: =$AD61 -> 500
B99: JAFF | C99: SONH | D99: 33.666667 | E99: 0 | F99: 0 | G99: 0 | H99: 0 | I99: 0 | J99: 0 | K99: 0 | L99: 0 | M99: 0 | N99: 0 | O99: 0 | P99: 0 | Q99: 0 | R99: 0 | S99: 0 | T99: 0 | U99: 0 | V99: 0 | W99: =D99*SUM(E99:V99) -> 0 | AC99: HUDV | AG99: =$AD62 -> 1500 | AH99: =$AD62 -> 1500 | AI99: =$AD62 -> 1500 | AJ99: =$AD62 -> 1500 | AK99: =$AD62 -> 1500 | AL99: =$AD62 -> 1500 | AM99: =$AD62 -> 1500 | AN99: =$AD62 -> 1500 | ... AX99: =$AD62 -> 1500
B100: JAFF | C100: UVLY | D100: 33.666667 | E100: 0 | F100: 0 | G100: 0 | H100: 0 | I100: 0 | J100: 0 | K100: 0 | L100: 0 | M100: 23.699944 | N100: 27.25002 | O100: 27.25002 | P100: 21.800016 | Q100: 0 | R100: 0 | S100: 0 | T100: 0 | U100: 0 | V100: 100 | W100: =D100*SUM(E100:V100) -> 6733.3333 | AC100: NCMA | AG100: =$AD63 -> 1000 | AH100: =$AD63 -> 1000 | AI100: =$AD63 -> 1000 | AJ100: =$AD63 -> 1000 | AK100: =$AD63 -> 1000 | AL100: =$AD63 -> 1000 | AM100: =$AD63 -> 1000 | AN100: =$AD63 -> 1000 | ... AX100: =$AD63 -> 1000
B101: JAFF | C101: WTMA | D101: 50.333333 | E101: 0 | F101: 0 | G101: 0 | H101: 0 | I101: 0 | J101: 0 | K101: 0 | L101: 0 | M101: 0 | N101: 0 | O101: 0 | P101: 0 | Q101: 0 | R101: 0 | S101: 0 | T101: 0 | U101: 0 | V101: 0 | W101: =D101*SUM(E101:V101) -> 0 | AC101: NJER | AG101: =$AD64 -> 1000 | AH101: =$AD64 -> 1000 | AI101: =$AD64 -> 1000 | AJ101: =$AD64 -> 1000 | AK101: =$AD64 -> 1000 | AL101: =$AD64 -> 1000 | AM101: =$AD64 -> 1000 | AN101: =$AD64 -> 1000 | ... AX101: =$AD64 -> 1000
B102: MICH | C102: OHIO | D102: 66.916667 | E102: 0 | F102: 0 | G102: 0 | H102: 0 | I102: 0 | J102: 0 | K102: 0 | L102: 0 | M102: 0 | N102: 0 | O102: 0 | P102: 0 | Q102: 0 | R102: 0 | S102: 0 | T102: 0 | U102: 0 | V102: 0 | W102: =D102*SUM(E102:V102) -> 0 | AC102: OHIO | AG102: =$AD65 -> 1200 | AH102: =$AD65 -> 1200 | AI102: =$AD65 -> 1200 | AJ102: =$AD65 -> 1200 | AK102: =$AD65 -> 1200 | AL102: =$AD65 -> 1200 | AM102: =$AD65 -> 1200 | AN102: =$AD65 -> 1200 | ... AX102: =$AD65 -> 1200
B103: MICH | C103: WTMA | D103: 66.916667 | E103: 0 | F103: 0 | G103: 0 | H103: 0 | I103: 0 | J103: 0 | K103: 0 | L103: 0 | M103: 100 | N103: 0 | O103: 0 | P103: 0 | Q103: 0 | R103: 0 | S103: 0 | T103: 0 | U103: 0 | V103: 100 | W103: =D103*SUM(E103:V103) -> 13383.333 | AC103: SCST | AG103: =$AD66 -> 500 | AH103: =$AD66 -> 500 | AI103: =$AD66 -> 500 | AJ103: =$AD66 -> 500 | AK103: =$AD66 -> 500 | AL103: =$AD66 -> 500 | AM103: =$AD66 -> 500 | AN103: =$AD66 -> 500 | ... AX103: =$AD66 -> 500
B104: PRIN | C104: BERK | D104: 183.58333 | E104: 0 | F104: 0 | G104: 0 | H104: 0 | I104: 0 | J104: 0 | K104: 188.57666 | L104: 189.72484 | M104: 168.08058 | N104: 0 | O104: 0 | P104: 0 | Q104: 0 | R104: 0 | S104: 0 | T104: 0 | U104: 0 | V104: 618.43576 | W104: =D104*SUM(E104:V104) -> 213841.14 | AC104: SEMA | AG104: =$AD67 -> 500 | AH104: =$AD67 -> 500 | AI104: =$AD67 -> 500 | AJ104: =$AD67 -> 500 | AK104: =$AD67 -> 500 | AL104: =$AD67 -> 500 | AM104: =$AD67 -> 500 | AN104: =$AD67 -> 500 | ... AX104: =$AD67 -> 500
B105: PRIN | C105: CJER | D105: 216.91667 | E105: 0 | F105: 0 | G105: 0 | H105: 0 | I105: 0 | J105: 0 | K105: 0 | L105: 0 | M105: 0 | N105: 0 | O105: 0 | P105: 0 | Q105: 0 | R105: 0 | S105: 0 | T105: 0 | U105: 0 | V105: 0 | W105: =D105*SUM(E105:V105) -> 0 | AC105: SONH | AG105: =$AD68 -> 2000 | AH105: =$AD68 -> 2000 | AI105: =$AD68 -> 2000 | AJ105: =$AD68 -> 2000 | AK105: =$AD68 -> 2000 | AL105: =$AD68 -> 2000 | AM105: =$AD68 -> 2000 | AN105: =$AD68 -> 2000 | ... AX105: =$AD68 -> 2000
B106: PRIN | C106: CTRI | D106: 190.25 | E106: 0 | F106: 0 | G106: 0 | H106: 0 | I106: 0 | J106: 0 | K106: 0 | L106: 0 | M106: 0 | N106: 0 | O106: 0 | P106: 0 | Q106: 0 | R106: 0 | S106: 0 | T106: 0 | U106: 0 | V106: 281.98687 | W106: =D106*SUM(E106:V106) -> 53648.002 | AC106: UVLY | AG106: =$AD69 -> 2500 | AH106: =$AD69 -> 2500 | AI106: =$AD69 -> 2500 | AJ106: =$AD69 -> 2500 | AK106: =$AD69 -> 2500 | AL106: =$AD69 -> 2500 | AM106: =$AD69 -> 2500 | AN106: =$AD69 -> 2500 | ... AX106: =$AD69 -> 2500
... B108: PRIN | C108: HUDV | D108: 233.58333 | E108: 0 | F108: 0 | G108: 0 | H108: 0 | I108: 0 | J108: 0 | K108: 0 | L108: 0 | M108: 0 | N108: 0 | O108: 0 | P108: 0 | Q108: 0 | R108: 0 | S108: 0 | T108: 0 | U108: 0 | V108: 0 | W108: =D108*SUM(E108:V108) -> 0 | AC108: WTMA | AG108: =$AD71 -> 7000 | AH108: =$AD71 -> 7000 | AI108: =$AD71 -> 7000 | AJ108: =$AD71 -> 7000 | AK108: =$AD71 -> 7000 | AL108: =$AD71 -> 7000 | AM108: =$AD71 -> 7000 | AN108: =$AD71 -> 7000 | ... AX108: =$AD71 -> 7000
B109: PRIN | C109: NCMA | D109: 216.91667 | E109: 0 | F109: 0 | G109: 0 | H109: 0 | I109: 0 | J109: 0 | K109: 0 | L109: 0 | M109: 0 | N109: 0 | O109: 0 | P109: 0 | Q109: 0 | R109: 0 | S109: 0 | T109: 0 | U109: 0 | V109: 0 | W109: =D109*SUM(E109:V109) -> 0
B110: PRIN | C110: SEMA | D110: 216.91667 | E110: 0 | F110: 0 | G110: 0 | H110: 0 | I110: 0 | J110: 0 | K110: 0 | L110: 0 | M110: 0 | N110: 0 | O110: 0 | P110: 0 | Q110: 0 | R110: 0 | S110: 0 | T110: 0 | U110: 0 | V110: 0 | W110: =D110*SUM(E110:V110) -> 0
...

Sheet RegionalDemand
A1: This Sheet takes the forecast by region (rows 7 - 20) and converts it into a forecast by type of wood (HW, SW), and inflates it by 5%, according to the WPD planning policy
A2: The final demand forecast (rows 28 to 55) is the demand forecast used in the planning model (rows 286 to 313 on Planning Model sheet)
A4: Demand by Region in Tons, including % hardwood
A6: RegionID | B6: RegionName | C6: HW | D6: 44256 | E6: 44287 | F6: 44317 | G6: 44348 | H6: 44378 | I6: 44409 | J6: 44440 | K6: 44470 | L6: 44501 | M6: 44531 | N6: 44562 | O6: 44593 | P6: 44621 | Q6: 44652 | R6: 44682 | S6: 44713 | T6: 44743 | U6: 44774
A7: BERK | B7: Berkshire | C7: 0.25 | D7: 178.2 | E7: 263.7765 | F7: 383.454 | G7: 616.248 | H7: 537.03 | I7: 523.5435 | J7: 810.891 | K7: 812.349 | L7: 342.873 | M7: 183.951 | N7: 183.951 | O7: 147.1608 | P7: 267.3 | Q7: 395.66475 | R7: 575.181 | S7: 924.372 | T7: 805.545 | U7: 785.31525
A8: CJER | B8: Central NJ | C8: 0.1 | D8: 36 | E8: 36 | F8: 54 | G8: 27 | H8: 45 | I8: 54 | J8: 90 | K8: 135 | L8: 135 | M8: 108 | N8: 72 | O8: 72 | P8: 63 | Q8: 54 | R8: 36 | S8: 27 | T8: 18 | U8: 18
A9: CTRI | B9: East CT-RI | C9: 0.15 | D9: 77.4 | E9: 194.472 | F9: 281.376 | G9: 401.112 | H9: 614.736 | I9: 826.992 | J9: 684.504 | K9: 510.984 | L9: 246.672 | M9: 141.912 | N9: 141.912 | O9: 113.5296 | P9: 116.1 | Q9: 291.708 | R9: 422.064 | S9: 601.668 | T9: 922.104 | U9: 1240.488
A10: DEME | B10: Downeast ME | C10: 0.3 | D10: 73.8 | E10: 106.848 | F10: 298.728 | G10: 564.048 | H10: 298.368 | I10: 221.112 | J10: 209.736 | K10: 174.312 | L10: 79.236 | M10: 57.744 | N10: 57.744 | O10: 46.1952 | P10: 110.7 | Q10: 160.272 | R10: 448.092 | S10: 846.072 | T10: 447.552 | U10: 331.668
A11: HUDV | B11: Hudson Valley | C11: 0.15 | D11: 288 | E11: 491.56875 | F11: 605.57625 | G11: 938.79 | H11: 1179.8663 | I11: 1185.3337 | J11: 969.26625 | K11: 944.35875 | L11: 573.48 | M11: 323.69625 | N11: 323.69625 | O11: 258.957 | P11: 432 | Q11: 737.35312 | R11: 908.36437 | S11: 1408.185 | T11: 1769.7994 | U11: 1778.0006
A12: NCMA | B12: N-Central Mass | C12: 0.2 | D12: 240.75 | E12: 611.82 | F12: 843.75 | G12: 1208.97 | H12: 1727.55 | I12: 1898.73 | J12: 2063.79 | K12: 1567.17 | L12: 724.14 | M12: 369.36 | N12: 369.36 | O12: 295.488 | P12: 361.125 | Q12: 917.73 | R12: 1265.625 | S12: 1813.455 | T12: 2591.325 | U12: 2848.095
A13: NJER | B13: North NJ | C13: 0.1 | D13: 31.5 | E13: 77.22 | F13: 172.44 | G13: 171.09 | H13: 213.21 | I13: 255.6 | J13: 301.59 | K13: 393.21 | L13: 169.47 | M13: 113.49 | N13: 113.49 | O13: 90.792 | P13: 47.25 | Q13: 115.83 | R13: 258.66 | S13: 256.635 | T13: 319.815 | U13: 383.4
A14: OHIO | B14: Ohio | C14: 0.15 | D14: 30.6 | E14: 34.128 | F14: 26.892 | G14: 34.722 | H14: 49.302 | I14: 59.508 | J14: 51.516 | K14: 91.908 | L14: 86.4 | M14: 58.914 | N14: 58.914 | O14: 47.1312 | P14: 45.9 | Q14: 51.192 | R14: 40.338 | S14: 52.083 | T14: 73.953 | U14: 89.262
A15: SCST | B15: MA-ME Seacoast | C15: 0.2 | D15: 79.2 | E15: 519.21 | F15: 991.359 | G15: 1517.454 | H15: 1787.508 | I15: 1479.546 | J15: 1400.247 | K15: 1173.042 | L15: 535.086 | M15: 308.124 | N15: 308.124 | O15: 246.4992 | P15: 118.8 | Q15: 778.815 | R15: 1487.0385 | S15: 2276.181 | T15: 2681.262 | U15: 2219.319
A16: SEMA | B16: SE Mass-RI | C16: 0.15 | D16: 79.2 | E16: 258.111 | F16: 395.766 | G16: 499.905 | H16: 964.341 | I16: 1072.449 | J16: 1277.073 | K16: 769.419 | L16: 382.284 | M16: 265.734 | N16: 265.734 | O16: 212.5872 | P16: 118.8 | Q16: 387.1665 | R16: 593.649 | S16: 749.8575 | T16: 1446.5115 | U16: 1608.6735
A17: SONH | B17: NH South | C17: 0.3 | D17: 153 | E17: 374.22 | F17: 656.343 | G17: 1191.348 | H17: 1384.938 | I17: 1165.185 | J17: 1057.131 | K17: 992.007 | L17: 492.156 | M17: 810.405 | N17: 450 | O17: 360 | P17: 229.5 | Q17: 561.33 | R17: 984.5145 | S17: 1787.022 | T17: 2077.407 | U17: 1747.7775
A18: UVLY | B18: NH Upper Valley | C18: 0.3 | D18: 45 | E18: 104.571 | F18: 166.536 | G18: 331.776 | H18: 285.12 | I18: 296.055 | J18: 335.745 | K18: 203.148 | L18: 110.079 | M18: 86.508 | N18: 86.508 | O18: 69.2064 | P18: 67.5 | Q18: 156.8565 | R18: 249.804 | S18: 497.664 | T18: 427.68 | U18: 444.0825
... A20: WTMA | B20: West Mass | C20: 0.2 | D20: 51.75 | E20: 102.33 | F20: 119.5425 | G20: 189.945 | H20: 304.155 | I20: 367.6725 | J20: 389.0025 | K20: 287.4825 | L20: 180.1575 | M20: 118.5975 | N20: 118.5975 | O20: 94.878 | P20: 77.625 | Q20: 153.495 | R20: 179.31375 | S20: 284.9175 | T20: 456.2325 | U20: 551.50875
C22: Total | D22: =SUM(D7:D20) -> 1400.4 | E22: =SUM(E7:E20) -> 3505.4032 | F22: =SUM(F7:F20) -> 5483.7787 | G22: =SUM(G7:G20) -> 8309.088 | H22: =SUM(H7:H20) -> 10373.276 | I22: =SUM(I7:I20) -> 10552.903 | J22: =SUM(J7:J20) -> 10930.732 | K22: =SUM(K7:K20) -> 9009.9022 | ... U22: =SUM(U7:U20) -> 15766.354
C23: Hardwood | D23: =SUMPRODUCT($C7:$C18,D7:D18) -> 268.11 | E23: =SUMPRODUCT($C7:$C18,E7:E18) -> 625.90579 | F23: =SUMPRODUCT($C7:$C18,F7:F18) -> 1018.4529 | G23: =SUMPRODUCT($C7:$C18,G7:G18) -> 1626.4868 | H23: =SUMPRODUCT($C7:$C18,H7:H18) -> 1874.8547 | I23: =SUMPRODUCT($C7:$C18,I7:I18) -> 1813.8491 | J23: =SUMPRODUCT($C7:$C18,J7:J18) -> 1862.8266 | K23: =SUMPRODUCT($C7:$C18,K7:K18) -> 1562.2912 | ... U23: =SUMPRODUCT($C7:$C18,U7:U18) -> 2714.4736
A25: demand muliplier | C25: 1.05
A27: Product | B27: RegionID | C27: RegionName | D27: 44256 | E27: 44287 | F27: 44317 | G27: 44348 | H27: 44378 | I27: 44409 | J27: 44440 | K27: 44470 | L27: 44501 | M27: 44531 | N27: 44562 | O27: 44593 | P27: 44621 | Q27: 44652 | R27: 44682 | S27: 44713 | T27: 44743 | U27: 44774
A28: HW | B28: BERK | C28: Berkshire | D28: =$C$25*$C7*D7 -> 46.7775 | E28: =$C$25*$C7*E7 -> 69.241331 | F28: =$C$25*$C7*F7 -> 100.65668 | G28: =$C$25*$C7*G7 -> 161.7651 | H28: =$C$25*$C7*H7 -> 140.97037 | I28: =$C$25*$C7*I7 -> 137.43017 | J28: =$C$25*$C7*J7 -> 212.85889 | K28: =$C$25*$C7*K7 -> 213.24161 | ... U28: =$C$25*$C7*U7 -> 206.14525
A29: HW | B29: CJER | C29: Central NJ | D29: =$C$25*$C8*D8 -> 3.78 | E29: =$C$25*$C8*E8 -> 3.78 | F29: =$C$25*$C8*F8 -> 5.67 | G29: =$C$25*$C8*G8 -> 2.835 | H29: =$C$25*$C8*H8 -> 4.725 | I29: =$C$25*$C8*I8 -> 5.67 | J29: =$C$25*$C8*J8 -> 9.45 | K29: =$C$25*$C8*K8 -> 14.175 | ... U29: =$C$25*$C8*U8 -> 1.89
A30: HW | B30: CTRI | C30: East CT-RI | D30: =$C$25*$C9*D9 -> 12.1905 | E30: =$C$25*$C9*E9 -> 30.62934 | F30: =$C$25*$C9*F9 -> 44.31672 | G30: =$C$25*$C9*G9 -> 63.17514 | H30: =$C$25*$C9*H9 -> 96.82092 | I30: =$C$25*$C9*I9 -> 130.25124 | J30: =$C$25*$C9*J9 -> 107.80938 | K30: =$C$25*$C9*K9 -> 80.47998 | ... U30: =$C$25*$C9*U9 -> 195.37686
A31: HW | B31: DEME | C31: Downeast ME | D31: =$C$25*$C10*D10 -> 23.247 | E31: =$C$25*$C10*E10 -> 33.65712 | F31: =$C$25*$C10*F10 -> 94.09932 | G31: =$C$25*$C10*G10 -> 177.67512 | H31: =$C$25*$C10*H10 -> 93.98592 | I31: =$C$25*$C10*I10 -> 69.65028 | J31: =$C$25*$C10*J10 -> 66.06684 | K31: =$C$25*$C10*K10 -> 54.90828 | ... U31: =$C$25*$C10*U10 -> 104.47542
A32: HW | B32: HUDV | C32: Hudson Valley | D32: =$C$25*$C11*D11 -> 45.36 | E32: =$C$25*$C11*E11 -> 77.422078 | F32: =$C$25*$C11*F11 -> 95.378259 | G32: =$C$25*$C11*G11 -> 147.85942 | H32: =$C$25*$C11*H11 -> 185.82893 | I32: =$C$25*$C11*I11 -> 186.69007 | J32: =$C$25*$C11*J11 -> 152.65943 | K32: =$C$25*$C11*K11 -> 148.7365 | ... U32: =$C$25*$C11*U11 -> 280.0351
A33: HW | B33: NCMA | C33: N-Central Mass | D33: =$C$25*$C12*D12 -> 50.5575 | E33: =$C$25*$C12*E12 -> 128.4822 | F33: =$C$25*$C12*F12 -> 177.1875 | G33: =$C$25*$C12*G12 -> 253.8837 | H33: =$C$25*$C12*H12 -> 362.7855 | I33: =$C$25*$C12*I12 -> 398.7333 | J33: =$C$25*$C12*J12 -> 433.3959 | K33: =$C$25*$C12*K12 -> 329.1057 | ... U33: =$C$25*$C12*U12 -> 598.09995
A34: HW | B34: NJER | C34: North NJ | D34: =$C$25*$C13*D13 -> 3.3075 | E34: =$C$25*$C13*E13 -> 8.1081 | F34: =$C$25*$C13*F13 -> 18.1062 | G34: =$C$25*$C13*G13 -> 17.96445 | H34: =$C$25*$C13*H13 -> 22.38705 | I34: =$C$25*$C13*I13 -> 26.838 | J34: =$C$25*$C13*J13 -> 31.66695 | K34: =$C$25*$C13*K13 -> 41.28705 | ... U34: =$C$25*$C13*U13 -> 40.257
A35: HW | B35: OHIO | C35: Ohio | D35: =$C$25*$C14*D14 -> 4.8195 | E35: =$C$25*$C14*E14 -> 5.37516 | F35: =$C$25*$C14*F14 -> 4.23549 | G35: =$C$25*$C14*G14 -> 5.468715 | H35: =$C$25*$C14*H14 -> 7.765065 | I35: =$C$25*$C14*I14 -> 9.37251 | J35: =$C$25*$C14*J14 -> 8.11377 | K35: =$C$25*$C14*K14 -> 14.47551 | ... U35: =$C$25*$C14*U14 -> 14.058765
A36: HW | B36: SCST | C36: MA-ME Seacoast | D36: =$C$25*$C15*D15 -> 16.632 | E36: =$C$25*$C15*E15 -> 109.0341 | F36: =$C$25*$C15*F15 -> 208.18539 | G36: =$C$25*$C15*G15 -> 318.66534 | H36: =$C$25*$C15*H15 -> 375.37668 | I36: =$C$25*$C15*I15 -> 310.70466 | J36: =$C$25*$C15*J15 -> 294.05187 | K36: =$C$25*$C15*K15 -> 246.33882 | ... U36: =$C$25*$C15*U15 -> 466.05699
A37: HW | B37: SEMA | C37: SE Mass-RI | D37: =$C$25*$C16*D16 -> 12.474 | E37: =$C$25*$C16*E16 -> 40.652482 | F37: =$C$25*$C16*F16 -> 62.333145 | G37: =$C$25*$C16*G16 -> 78.735038 | H37: =$C$25*$C16*H16 -> 151.88371 | I37: =$C$25*$C16*I16 -> 168.91072 | J37: =$C$25*$C16*J16 -> 201.139 | K37: =$C$25*$C16*K16 -> 121.18349 | ... U37: =$C$25*$C16*U16 -> 253.36608
A38: HW | B38: SONH | C38: NH South | D38: =$C$25*$C17*D17 -> 48.195 | E38: =$C$25*$C17*E17 -> 117.8793 | F38: =$C$25*$C17*F17 -> 206.74804 | G38: =$C$25*$C17*G17 -> 375.27462 | H38: =$C$25*$C17*H17 -> 436.25547 | I38: =$C$25*$C17*I17 -> 367.03327 | J38: =$C$25*$C17*J17 -> 332.99626 | K38: =$C$25*$C17*K17 -> 312.4822 | ... U38: =$C$25*$C17*U17 -> 550.54991
A39: HW | B39: UVLY | C39: NH Upper Valley | D39: =$C$25*$C18*D18 -> 14.175 | E39: =$C$25*$C18*E18 -> 32.939865 | F39: =$C$25*$C18*F18 -> 52.45884 | G39: =$C$25*$C18*G18 -> 104.50944 | H39: =$C$25*$C18*H18 -> 89.8128 | I39: =$C$25*$C18*I18 -> 93.257325 | J39: =$C$25*$C18*J18 -> 105.75968 | K39: =$C$25*$C18*K18 -> 63.99162 | ... U39: =$C$25*$C18*U18 -> 139.88599
... A41: HW | B41: WTMA | C41: West Mass | D41: =$C$25*$C20*D20 -> 10.8675 | E41: =$C$25*$C20*E20 -> 21.4893 | F41: =$C$25*$C20*F20 -> 25.103925 | G41: =$C$25*$C20*G20 -> 39.88845 | H41: =$C$25*$C20*H20 -> 63.87255 | I41: =$C$25*$C20*I20 -> 77.211225 | J41: =$C$25*$C20*J20 -> 81.690525 | K41: =$C$25*$C20*K20 -> 60.371325 | ... U41: =$C$25*$C20*U20 -> 115.81684
A42: SW | B42: BERK | C42: Berkshire | D42: =$C$25*(1-$C7)*D7 -> 140.3325 | E42: =$C$25*(1-$C7)*E7 -> 207.72399 | F42: =$C$25*(1-$C7)*F7 -> 301.97003 | G42: =$C$25*(1-$C7)*G7 -> 485.2953 | H42: =$C$25*(1-$C7)*H7 -> 422.91113 | I42: =$C$25*(1-$C7)*I7 -> 412.29051 | J42: =$C$25*(1-$C7)*J7 -> 638.57666 | K42: =$C$25*(1-$C7)*K7 -> 639.72484 | ... U42: =$C$25*(1-$C7)*U7 -> 618.43576
A43: SW | B43: CJER | C43: Central NJ | D43: =$C$25*(1-$C8)*D8 -> 34.02 | E43: =$C$25*(1-$C8)*E8 -> 34.02 | F43: =$C$25*(1-$C8)*F8 -> 51.03 | G43: =$C$25*(1-$C8)*G8 -> 25.515 | H43: =$C$25*(1-$C8)*H8 -> 42.525 | I43: =$C$25*(1-$C8)*I8 -> 51.03 | J43: =$C$25*(1-$C8)*J8 -> 85.05 | K43: =$C$25*(1-$C8)*K8 -> 127.575 | ... U43: =$C$25*(1-$C8)*U8 -> 17.01
A44: SW | B44: CTRI | C44: East CT-RI | D44: =$C$25*(1-$C9)*D9 -> 69.0795 | E44: =$C$25*(1-$C9)*E9 -> 173.56626 | F44: =$C$25*(1-$C9)*F9 -> 251.12808 | G44: =$C$25*(1-$C9)*G9 -> 357.99246 | H44: =$C$25*(1-$C9)*H9 -> 548.65188 | I44: =$C$25*(1-$C9)*I9 -> 738.09036 | J44: =$C$25*(1-$C9)*J9 -> 610.91982 | K44: =$C$25*(1-$C9)*K9 -> 456.05322 | ... U44: =$C$25*(1-$C9)*U9 -> 1107.1355
A45: SW | B45: DEME | C45: Downeast ME | D45: =$C$25*(1-$C10)*D10 -> 54.243 | E45: =$C$25*(1-$C10)*E10 -> 78.53328 | F45: =$C$25*(1-$C10)*F10 -> 219.56508 | G45: =$C$25*(1-$C10)*G10 -> 414.57528 | H45: =$C$25*(1-$C10)*H10 -> 219.30048 | I45: =$C$25*(1-$C10)*I10 -> 162.51732 | J45: =$C$25*(1-$C10)*J10 -> 154.15596 | K45: =$C$25*(1-$C10)*K10 -> 128.11932 | ... U45: =$C$25*(1-$C10)*U10 -> 243.77598
A46: SW | B46: HUDV | C46: Hudson Valley | D46: =$C$25*(1-$C11)*D11 -> 257.04 | E46: =$C$25*(1-$C11)*E11 -> 438.72511 | F46: =$C$25*(1-$C11)*F11 -> 540.4768 | G46: =$C$25*(1-$C11)*G11 -> 837.87007 | H46: =$C$25*(1-$C11)*H11 -> 1053.0306 | I46: =$C$25*(1-$C11)*I11 -> 1057.9104 | J46: =$C$25*(1-$C11)*J11 -> 865.07013 | K46: =$C$25*(1-$C11)*K11 -> 842.84018 | ... U46: =$C$25*(1-$C11)*U11 -> 1586.8656
A47: SW | B47: NCMA | C47: N-Central Mass | D47: =$C$25*(1-$C12)*D12 -> 202.23 | E47: =$C$25*(1-$C12)*E12 -> 513.9288 | F47: =$C$25*(1-$C12)*F12 -> 708.75 | G47: =$C$25*(1-$C12)*G12 -> 1015.5348 | H47: =$C$25*(1-$C12)*H12 -> 1451.142 | I47: =$C$25*(1-$C12)*I12 -> 1594.9332 | J47: =$C$25*(1-$C12)*J12 -> 1733.5836 | K47: =$C$25*(1-$C12)*K12 -> 1316.4228 | ... U47: =$C$25*(1-$C12)*U12 -> 2392.3998
A48: SW | B48: NJER | C48: North NJ | D48: =$C$25*(1-$C13)*D13 -> 29.7675 | E48: =$C$25*(1-$C13)*E13 -> 72.9729 | F48: =$C$25*(1-$C13)*F13 -> 162.9558 | G48: =$C$25*(1-$C13)*G13 -> 161.68005 | H48: =$C$25*(1-$C13)*H13 -> 201.48345 | I48: =$C$25*(1-$C13)*I13 -> 241.542 | J48: =$C$25*(1-$C13)*J13 -> 285.00255 | K48: =$C$25*(1-$C13)*K13 -> 371.58345 | ... U48: =$C$25*(1-$C13)*U13 -> 362.313
A49: SW | B49: OHIO | C49: Ohio | D49: =$C$25*(1-$C14)*D14 -> 27.3105 | E49: =$C$25*(1-$C14)*E14 -> 30.45924 | F49: =$C$25*(1-$C14)*F14 -> 24.00111 | G49: =$C$25*(1-$C14)*G14 -> 30.989385 | H49: =$C$25*(1-$C14)*H14 -> 44.002035 | I49: =$C$25*(1-$C14)*I14 -> 53.11089 | J49: =$C$25*(1-$C14)*J14 -> 45.97803 | K49: =$C$25*(1-$C14)*K14 -> 82.02789 | ... U49: =$C$25*(1-$C14)*U14 -> 79.666335
A50: SW | B50: SCST | C50: MA-ME Seacoast | D50: =$C$25*(1-$C15)*D15 -> 66.528 | E50: =$C$25*(1-$C15)*E15 -> 436.1364 | F50: =$C$25*(1-$C15)*F15 -> 832.74156 | G50: =$C$25*(1-$C15)*G15 -> 1274.6614 | H50: =$C$25*(1-$C15)*H15 -> 1501.5067 | I50: =$C$25*(1-$C15)*I15 -> 1242.8186 | J50: =$C$25*(1-$C15)*J15 -> 1176.2075 | K50: =$C$25*(1-$C15)*K15 -> 985.35528 | ... U50: =$C$25*(1-$C15)*U15 -> 1864.228
A51: SW | B51: SEMA | C51: SE Mass-RI | D51: =$C$25*(1-$C16)*D16 -> 70.686 | E51: =$C$25*(1-$C16)*E16 -> 230.36407 | F51: =$C$25*(1-$C16)*F16 -> 353.22116 | G51: =$C$25*(1-$C16)*G16 -> 446.16521 | H51: =$C$25*(1-$C16)*H16 -> 860.67434 | I51: =$C$25*(1-$C16)*I16 -> 957.16073 | J51: =$C$25*(1-$C16)*J16 -> 1139.7877 | K51: =$C$25*(1-$C16)*K16 -> 686.70646 | ... U51: =$C$25*(1-$C16)*U16 -> 1435.7411
A52: SW | B52: SONH | C52: NH South | D52: =$C$25*(1-$C17)*D17 -> 112.455 | E52: =$C$25*(1-$C17)*E17 -> 275.0517 | F52: =$C$25*(1-$C17)*F17 -> 482.4121 | G52: =$C$25*(1-$C17)*G17 -> 875.64078 | H52: =$C$25*(1-$C17)*H17 -> 1017.9294 | I52: =$C$25*(1-$C17)*I17 -> 856.41097 | J52: =$C$25*(1-$C17)*J17 -> 776.99128 | K52: =$C$25*(1-$C17)*K17 -> 729.12514 | ... U52: =$C$25*(1-$C17)*U17 -> 1284.6165
A53: SW | B53: UVLY | C53: NH Upper Valley | D53: =$C$25*(1-$C18)*D18 -> 33.075 | E53: =$C$25*(1-$C18)*E18 -> 76.859685 | F53: =$C$25*(1-$C18)*F18 -> 122.40396 | G53: =$C$25*(1-$C18)*G18 -> 243.85536 | H53: =$C$25*(1-$C18)*H18 -> 209.5632 | I53: =$C$25*(1-$C18)*I18 -> 217.60042 | J53: =$C$25*(1-$C18)*J18 -> 246.77257 | K53: =$C$25*(1-$C18)*K18 -> 149.31378 | ... U53: =$C$25*(1-$C18)*U18 -> 326.40064
... A55: SW | B55: WTMA | C55: West Mass | D55: =$C$25*(1-$C20)*D20 -> 43.47 | E55: =$C$25*(1-$C20)*E20 -> 85.9572 | F55: =$C$25*(1-$C20)*F20 -> 100.4157 | G55: =$C$25*(1-$C20)*G20 -> 159.5538 | H55: =$C$25*(1-$C20)*H20 -> 255.4902 | I55: =$C$25*(1-$C20)*I20 -> 308.8449 | J55: =$C$25*(1-$C20)*J20 -> 326.7621 | K55: =$C$25*(1-$C20)*K20 -> 241.4853 | ... U55: =$C$25*(1-$C20)*U20 -> 463.26735
D56: 44256 | E56: 44287 | F56: 44317 | G56: 44348 | H56: 44378 | I56: 44409 | J56: 44440 | K56: 44470 | L56: 44501 | M56: 44531 | N56: 44562 | O56: 44593 | P56: 44621 | Q56: 44652 | R56: 44682 | S56: 44713 | T56: 44743 | U56: 44774
C57: HW | D57: =SUM(D28:D41) -> 298.053 | E57: =SUM(E28:E41) -> 730.84304 | F57: =SUM(F28:F41) -> 1171.342 | G57: =SUM(G28:G41) -> 1844.8266 | H57: =SUM(H28:H41) -> 2187.1589 | I57: =SUM(I28:I41) -> 2162.433 | J57: =SUM(J28:J41) -> 2240.8713 | K57: =SUM(K28:K41) -> 1851.2702 | ... U57: =SUM(U28:U41) -> 3237.0345
C58: SW | D58: =SUM(D42:D55) -> 1172.367 | E58: =SUM(E42:E55) -> 2949.8304 | F58: =SUM(F42:F55) -> 4586.6257 | G58: =SUM(G42:G55) -> 6879.7158 | H58: =SUM(H42:H55) -> 8704.7812 | I58: =SUM(I42:I55) -> 8918.1149 | J58: =SUM(J42:J55) -> 9236.397 | K58: =SUM(K42:K55) -> 7609.1271 | ... U58: =SUM(U42:U55) -> 13317.637
C59: Total | D59: =D57+D58 -> 1470.42 | E59: =E57+E58 -> 3680.6734 | F59: =F57+F58 -> 5757.9677 | G59: =G57+G58 -> 8724.5424 | H59: =H57+H58 -> 10891.94 | I59: =I57+I58 -> 11080.548 | J59: =J57+J58 -> 11477.268 | K59: =K57+K58 -> 9460.3974 | ... U59: =U57+U58 -> 16554.672
D93: 44256 | E93: 44287 | F93: 44317 | G93: 44348 | H93: 44378 | I93: 44409 | J93: 44440 | K93: 44470 | L93: 44501 | M93: 44531 | N93: 44562 | O93: 44593 | P93: 44621 | Q93: 44652 | R93: 44682 | S93: 44713 | T93: 44743 | U93: 44774
C94: Upper Bound | D94: =SUM('Planning Model'!E219:E226) -> 7980 | E94: =SUM('Planning Model'!F219:F226) -> 7980 | F94: =SUM('Planning Model'!G219:G226) -> 7480 | G94: =SUM('Planning Model'!H219:H226) -> 7480 | H94: =SUM('Planning Model'!I219:I226) -> 7480 | I94: =SUM('Planning Model'!J219:J226) -> 7980 | J94: =SUM('Planning Model'!K219:K226) -> 7980 | K94: =SUM('Planning Model'!L219:L226) -> 7760 | ... U94: =SUM('Planning Model'!V219:V226) -> 10760
C95: Lower Bound | D95: =SUM('Planning Model'!E208:E215) -> 5870 | E95: =SUM('Planning Model'!F208:F215) -> 5870 | F95: =SUM('Planning Model'!G208:G215) -> 5620 | G95: =SUM('Planning Model'!H208:H215) -> 5620 | H95: =SUM('Planning Model'!I208:I215) -> 5620 | I95: =SUM('Planning Model'!J208:J215) -> 6070 | J95: =SUM('Planning Model'!K208:K215) -> 6070 | K95: =SUM('Planning Model'!L208:L215) -> 5890 | ... U95: =SUM('Planning Model'!V208:V215) -> 8075
